{
  "header": {
    "title": "Cho Thuê Căn Hộ Chung Cư, Giá Rẻ, View Đẹp, Mới Nhất 2024",
    "describe": "Cho thuê căn hộ - Kênh đăng tin cho thuê căn hộ số 1: giá rẻ, chính chủ, đầy đủ tiện nghi. Cho thuê chung cư với nhiều mức giá, diện tích cho thuê khác nhau."
  },
  "body": [
    {
      "images": [
        {
          "img": "https://pt123.cdn.static123.com/images/thumbs/900x600/fit/2023/07/27/hanh-lang-1_1690431683.png",
          "alt": "Phòng bancon lớn đối diện Landmark 81, Pearl Plaza"
        },
        {
          "img": "https://pt123.cdn.static123.com/images/thumbs/900x600/fit/2023/07/26/img-0859_1690378046.jpg",
          "alt": "Phòng bancon lớn đối diện Landmark 81, Pearl Plaza"
        },
        {
          "img": "https://pt123.cdn.static123.com/images/thumbs/900x600/fit/2023/07/26/img-0860_1690378047.jpg",
          "alt": "Phòng bancon lớn đối diện Landmark 81, Pearl Plaza"
        },
        {
          "img": "https://pt123.cdn.static123.com/images/thumbs/900x600/fit/2023/07/26/img-0864_1690378051.jpg",
          "alt": "Phòng bancon lớn đối diện Landmark 81, Pearl Plaza"
        },
        {
          "img": "https://pt123.cdn.static123.com/images/thumbs/900x600/fit/2023/07/26/z2517676136431-96d8c3e305fd2ab662e56209ac8f5c85_1690378059.jpg",
          "alt": "Phòng bancon lớn đối diện Landmark 81, Pearl Plaza"
        },
        {
          "img": "https://pt123.cdn.static123.com/images/thumbs/900x600/fit/2023/07/26/z2517675458066-3b07a1725d133c9fe4f9c19a9dbb10d2_1690378056.jpg",
          "alt": "Phòng bancon lớn đối diện Landmark 81, Pearl Plaza"
        },
        {
          "img": "https://pt123.cdn.static123.com/images/thumbs/900x600/fit/2023/07/26/z2517675813432-8f8e4f470005bc00ee8e845c253acc26_1690378057.jpg",
          "alt": "Phòng bancon lớn đối diện Landmark 81, Pearl Plaza"
        },
        {
          "img": "https://pt123.cdn.static123.com/images/thumbs/900x600/fit/2023/07/26/z2517676469125-26d03c2c13c383d6b9d51ac0b5268e1a_1690378059.jpg",
          "alt": "Phòng bancon lớn đối diện Landmark 81, Pearl Plaza"
        },
        {
          "img": "https://pt123.cdn.static123.com/images/thumbs/900x600/fit/2023/07/27/nvs-2_1690431486.png",
          "alt": "Phòng bancon lớn đối diện Landmark 81, Pearl Plaza"
        },
        {
          "img": "https://pt123.cdn.static123.com/images/thumbs/900x600/fit/2023/07/27/nvs_1690431486.png",
          "alt": "Phòng bancon lớn đối diện Landmark 81, Pearl Plaza"
        },
        {
          "img": "https://pt123.cdn.static123.com/images/thumbs/900x600/fit/2023/07/27/hanh-lang-1_1690431683.png",
          "alt": "Phòng bancon lớn đối diện Landmark 81, Pearl Plaza"
        },
        {
          "img": "https://pt123.cdn.static123.com/images/thumbs/900x600/fit/2023/07/26/img-0859_1690378046.jpg",
          "alt": "Phòng bancon lớn đối diện Landmark 81, Pearl Plaza"
        }
      ],
      "headerDetail": {
        "title": "Phòng bancon lớn đối diện Landmark 81, Pearl Plaza",
        "star": "3",
        "class": {
          "content": "Chuyên mục: Cho thuê căn hộ dịch vụ Quận Bình Thạnh",
          "classType": "Cho thuê căn hộ dịch vụ Quận Bình Thạnh"
        },
        "address": "Địa chỉ: 135/37 Đường Nguyễn Hữu Cảnh, Phường 22, Quận Bình Thạnh, Hồ Chí Minh",
        "attributes": {
          "price": "6.2 triệu/tháng",
          "acreage": "30m2",
          "published": "Hôm nay",
          "hashtag": "631518"
        }
      },
      "mainContent": {
        "header": { "header": "Thông tin mô tả" },
        "content": [
          "PHÒNG CHO THUÊ - VỊ TRÍ ĐẸP, TIỆN NGHI",
          "VỊ TRÍ ĐẮC ĐỊA:",
          "Đường nội bộ rộng rãi, xe tải ra vào thoải mái.",
          "Khu dân cư an ninh, dân trí cao, gần chợ và siêu thị tiện lợi.",
          "Gần công viên, khu giải trí và bờ sông Vincom Central Park.",
          "Di chuyển nhanh chóng đến trung tâm các quận như Q1, Q2, Q3, Phú Nhuận (đường rộng, không kẹt xe).",
          "Gần các trường Đại học Hutech, Ngoại Thương, Hồng Bàng.",
          "Ngay cạnh khu trung tâm mua sắm Pearl Plaza (Coopmart Extra), Saigon Pearl, Vincom Landmark 81.",
          "Nhiều dịch vụ ăn uống và giải trí xung quanh.",
          "️ PHÒNG ĐẦY ĐỦ NỘI THẤT:",
          "Giường, nệm cao cấp cùng ga gối.",
          "WC riêng với trang thiết bị cao cấp, vòi sen và nước nóng không tốn điện.",
          "Bàn, ghế làm việc hiện đại.",
          "Tủ quần áo, kệ TV.",
          "Tủ lạnh và máy lạnh.",
          "Tủ bếp trên dưới.",
          "GIÁ ĐÃ BAO GỒM TẤT CẢ DỊCH VỤ VÀ TIỆN ÍCH SAU:",
          "Máy giặt, máy sấy quần áo.",
          "Bảo trì, sửa chữa.",
          "Chỗ để xe rộng rãi.",
          "Cửa vân tay an ninh.",
          "Hệ thống camera 24/24 (khu nhà xe và khu vực chung).",
          "Dịch vụ dọn vệ sinh hàng tuần (khu vực chung) và thu gom rác hàng ngày.",
          "Giờ giấc tự do, không chung chủ.",
          "Giá từ 6 triệu đến 7.2 triệu.",
          "Địa chỉ: 135/37 Nguyễn Hữu Cảnh, P22, Q. Bình Thạnh.",
          "Liên hệ A Thoại - 0962 42 42 61 để biết thêm chi tiết và xem phòng ngay hôm nay!",
          "ROOM FOR RENT - GREAT LOCATION, FULLY EQUIPPED",
          "PRIME LOCATION:",
          "Wide internal road (suitable for trucks), secure residential area, high-class neighborhood, close to convenient markets and supermarkets.",
          "Near parks, entertainment areas, and the riverside Vincom Central Park.",
          "Only 3-5 minutes to reach the city center of Districts 1, 2, 3, and Phu Nhuan (wide roads, no traffic jams).",
          "Close to universities like Hutech, Foreign Trade University, and Hong Bang University.",
          "Adjacent to shopping centers such as Pearl Plaza (Coopmart Extra), Saigon Pearl, and Vincom Landmark 81.",
          "Surrounded by various dining and entertainment services.",
          "️ FULLY FURNISHED ROOM:",
          "High-quality bed, mattress, sheets, blankets, and pillows.",
          "Private bathroom with high-class equipment, shower, and solar water heater (no electricity cost).",
          "Modern working desk and chair.",
          "Wardrobe, TV shelf.",
          "Refrigerator and air-conditioner.",
          "Kitchen for cooking.",
          "PRICE INCLUDES ALL SERVICES AND UTILITIES:",
          "Washer and dryer.",
          "Maintenance and repair.",
          "Spacious parking space.",
          "Secure fingerprint door access.",
          "24/7 camera surveillance (parking area and common areas).",
          "Weekly cleaning of common areas and daily trash collection.",
          "Flexible schedule, no live-in landlord.",
          "Prices range from 6.2 to 7.2 million VND.",
          "Address: 135/37 Nguyen Huu Canh, Ward 22, Binh Thanh District.",
          "Contact Mr. Thoai - 0962 42 42 61 for more details and to view the room today!"
        ]
      },
      "overView": {
        "header": { "header": "Đặc điểm tin đăng" },
        "content": [
          { "name": "Mã tin:", "content": "#631518" },
          {
            "name": "Khu vực",
            "content": "Cho thuê căn hộ dịch vụ Hồ Chí Minh"
          },
          { "name": "Loại tin rao:", "content": "Cho thuê căn hộ dịch vụ" },
          { "name": "Đối tượng thuê:", "content": "Tất cả" },
          { "name": "Gói tin:", "content": "Tin VIP 2" },
          { "name": "Ngày đăng:", "content": "Chủ Nhật, 17:57 12/05/2024" },
          { "name": "Ngày hết hạn:", "content": "Thứ 6, 17:57 17/05/2024" }
        ]
      },
      "contact": {
        "header": { "header": "Thông tin liên hệ" },
        "content": [
          { "name": "Liên hệ:", "content": "Thoại" },
          { "name": "Điện thoại:", "content": "0962424261" },
          { "name": "Zalo", "content": "0962424261" }
        ]
      }
    },
    {
      "images": [
        {
          "img": "https://pt123.cdn.static123.com/images/thumbs/900x600/fit/2024/05/12/4807569c5d60a8a48fe4eebfba2391a4_1715491747.jpg",
          "alt": "Căn Hộ 2PN 40m2 Ngay Chân Cầu Sài Gòn"
        },
        {
          "img": "https://pt123.cdn.static123.com/images/thumbs/900x600/fit/2024/05/12/1e22597ea83dc535d1fee28748775136_1715491737.jpg",
          "alt": "Căn Hộ 2PN 40m2 Ngay Chân Cầu Sài Gòn"
        },
        {
          "img": "https://pt123.cdn.static123.com/images/thumbs/900x600/fit/2024/05/12/2781206fd7e5a162242ebec7dff97c3e_1715491737.jpg",
          "alt": "Căn Hộ 2PN 40m2 Ngay Chân Cầu Sài Gòn"
        },
        {
          "img": "https://pt123.cdn.static123.com/images/thumbs/900x600/fit/2024/05/12/fa9bfb3475994446d11526669db916df_1715491739.jpg",
          "alt": "Căn Hộ 2PN 40m2 Ngay Chân Cầu Sài Gòn"
        },
        {
          "img": "https://pt123.cdn.static123.com/images/thumbs/900x600/fit/2024/05/12/cae238f17919716a8a6325a91699431c_1715491739.jpg",
          "alt": "Căn Hộ 2PN 40m2 Ngay Chân Cầu Sài Gòn"
        },
        {
          "img": "https://pt123.cdn.static123.com/images/thumbs/900x600/fit/2024/05/12/ed5d3219c15b05d49655c77f7a65c0d5_1715491742.jpg",
          "alt": "Căn Hộ 2PN 40m2 Ngay Chân Cầu Sài Gòn"
        },
        {
          "img": "https://pt123.cdn.static123.com/images/thumbs/900x600/fit/2024/05/12/40d410a3c9e7a035197ab5b0e8da6bd0_1715491745.jpg",
          "alt": "Căn Hộ 2PN 40m2 Ngay Chân Cầu Sài Gòn"
        },
        {
          "img": "https://pt123.cdn.static123.com/images/thumbs/900x600/fit/2024/05/12/8b28538fb46688cebc42eb46977f53fe_1715491745.jpg",
          "alt": "Căn Hộ 2PN 40m2 Ngay Chân Cầu Sài Gòn"
        },
        {
          "img": "https://pt123.cdn.static123.com/images/thumbs/900x600/fit/2024/05/12/9da3bfff709f2d82e487d13d71020d5d_1715491747.jpg",
          "alt": "Căn Hộ 2PN 40m2 Ngay Chân Cầu Sài Gòn"
        },
        {
          "img": "https://pt123.cdn.static123.com/images/thumbs/900x600/fit/2024/05/12/65805dfaada8cfe32834aac38da22867_1715491743.jpg",
          "alt": "Căn Hộ 2PN 40m2 Ngay Chân Cầu Sài Gòn"
        },
        {
          "img": "https://pt123.cdn.static123.com/images/thumbs/900x600/fit/2024/05/12/4807569c5d60a8a48fe4eebfba2391a4_1715491747.jpg",
          "alt": "Căn Hộ 2PN 40m2 Ngay Chân Cầu Sài Gòn"
        },
        {
          "img": "https://pt123.cdn.static123.com/images/thumbs/900x600/fit/2024/05/12/1e22597ea83dc535d1fee28748775136_1715491737.jpg",
          "alt": "Căn Hộ 2PN 40m2 Ngay Chân Cầu Sài Gòn"
        }
      ],
      "headerDetail": {
        "title": "Căn Hộ 2PN 40m2 Ngay Chân Cầu Sài Gòn",
        "star": "3",
        "class": {
          "content": "Chuyên mục: Cho thuê căn hộ dịch vụ Quận 2",
          "classType": "Cho thuê căn hộ dịch vụ Quận 2"
        },
        "address": "Địa chỉ: 137 Đường số 7, Phường An Phú, Quận 2, Hồ Chí Minh",
        "attributes": {
          "price": "11.5 triệu/tháng",
          "acreage": "40m2",
          "published": "Hôm nay",
          "hashtag": "654547"
        }
      },
      "mainContent": {
        "header": { "header": "Thông tin mô tả" },
        "content": [
          "2 PHÒNG NGỦ + 1 PHÒNG BẾP",
          "Có thể ở liền",
          "Full Ban công, cửa sổ",
          "Full nội thất",
          "Free xe",
          "Nhà mới đầy đủ tiện nghi chỉ dọn vào ở",
          "Cam kết như hình 100%",
          "Khách đến xem sớm để có sự lựa chọn tốt nhất",
          "️0932351513 Trần Phụng",
          ""
        ]
      },
      "overView": {
        "header": { "header": "Đặc điểm tin đăng" },
        "content": [
          { "name": "Mã tin:", "content": "#654547" },
          {
            "name": "Khu vực",
            "content": "Cho thuê căn hộ dịch vụ Hồ Chí Minh"
          },
          { "name": "Loại tin rao:", "content": "Cho thuê căn hộ dịch vụ" },
          { "name": "Đối tượng thuê:", "content": "Tất cả" },
          { "name": "Gói tin:", "content": "Tin VIP 2" },
          { "name": "Ngày đăng:", "content": "Chủ Nhật, 12:30 12/05/2024" },
          { "name": "Ngày hết hạn:", "content": "Thứ 6, 12:30 17/05/2024" }
        ]
      },
      "contact": {
        "header": { "header": "Thông tin liên hệ" },
        "content": [
          { "name": "Liên hệ:", "content": "Trần Phụng" },
          { "name": "Điện thoại:", "content": "0932351513" },
          { "name": "Zalo", "content": "0932351513" }
        ]
      }
    },
    {
      "images": [
        {
          "img": "https://pt123.cdn.static123.com/images/thumbs/900x600/fit/2024/05/10/4_1715333885.jpg",
          "alt": "Căn hộ mini cao cấp ngay Vạn Hạnh Mall, mới 100%, nội thất đầy đủ, có bảo vệ 24/7"
        },
        {
          "img": "https://pt123.cdn.static123.com/images/thumbs/900x600/fit/2024/05/10/1_1715333885.jpg",
          "alt": "Căn hộ mini cao cấp ngay Vạn Hạnh Mall, mới 100%, nội thất đầy đủ, có bảo vệ 24/7"
        },
        {
          "img": "https://pt123.cdn.static123.com/images/thumbs/900x600/fit/2024/05/10/2_1715333885.jpg",
          "alt": "Căn hộ mini cao cấp ngay Vạn Hạnh Mall, mới 100%, nội thất đầy đủ, có bảo vệ 24/7"
        },
        {
          "img": "https://pt123.cdn.static123.com/images/thumbs/900x600/fit/2024/05/10/3_1715333885.jpg",
          "alt": "Căn hộ mini cao cấp ngay Vạn Hạnh Mall, mới 100%, nội thất đầy đủ, có bảo vệ 24/7"
        },
        {
          "img": "https://pt123.cdn.static123.com/images/thumbs/900x600/fit/2024/05/10/4_1715333885.jpg",
          "alt": "Căn hộ mini cao cấp ngay Vạn Hạnh Mall, mới 100%, nội thất đầy đủ, có bảo vệ 24/7"
        },
        {
          "img": "https://pt123.cdn.static123.com/images/thumbs/900x600/fit/2024/05/10/1_1715333885.jpg",
          "alt": "Căn hộ mini cao cấp ngay Vạn Hạnh Mall, mới 100%, nội thất đầy đủ, có bảo vệ 24/7"
        }
      ],
      "headerDetail": {
        "title": "Căn hộ mini cao cấp ngay Vạn Hạnh Mall, mới 100%, nội thất đầy đủ, có bảo vệ 24/7",
        "star": "2",
        "class": {
          "content": "Chuyên mục: Cho thuê căn hộ mini Quận 10",
          "classType": "Cho thuê căn hộ mini Quận 10"
        },
        "address": "Địa chỉ: 662/6 Sư Vạn Hạnh, Phường 12, Quận 10, Hồ Chí Minh",
        "attributes": {
          "price": "5.5 triệu/tháng",
          "acreage": "30m2",
          "published": "Hôm nay",
          "hashtag": "654425"
        }
      },
      "mainContent": {
        "header": { "header": "Thông tin mô tả" },
        "content": [
          "Đc: 662/6 Sư Vạn Hạnh, Phường 12, Quận 19 ( ĐỐI DIỆN Vạn Hạnh Mall )",
          "Vị trí trung tâm Q.10, chỉ 10’ đi qua Tân Bình, Q.5, Q.1, Q.3",
          "Là trục đường lớn nối liền Lý Thường Kiệt, Thành Thái, Lê Đại Hành, Nguyễn Tri Phương",
          "Vị trí hẻm ô tô đường lớn, taxi đưa đón dễ dàng",
          "Bán kính 2km quanh nhà là Siêu thị, chợ, công viên, Rạp Phim, phòng Gym tiện cho mua sắm sinh hoạt, giải trí khi cần.",
          "--------",
          "️ TIỆN ÍCH",
          "Thiết kế tone màu nhẹ nhàng, sang trọng",
          "Tiện nghi, vật dụng được đang bị đầy đủ và sắp xếp hợp lý không gian như hình: tủ, giường nệm, tủ lạnh, máy lạnh, tủ đồ, góc kệ bếp, bàn ghế, tủ bếp…",
          "Phòng vệ sinh trong phòng riêng tư tiện lợi",
          "Máy giặt và sân phơi chung rộng rãi",
          "Hệ thống internet mạnh mẽ thỏa mãn giải trí, công việc",
          "Camera an ninh 24/24",
          "Bảo vệ 24h, giờ giấc tự do ra vào thoải mái",
          "----",
          "Giá chỉ 5.5tr/th",
          "Hãy gọi cho Mr Tùng 0932029986 để được TƯ VẤN MIỄN PHÍ và nhận ưu đãi nhé!!!",
          "",
          ""
        ]
      },
      "overView": {
        "header": { "header": "Đặc điểm tin đăng" },
        "content": [
          { "name": "Mã tin:", "content": "#654425" },
          { "name": "Khu vực", "content": "Cho thuê căn hộ mini Hồ Chí Minh" },
          { "name": "Loại tin rao:", "content": "Cho thuê căn hộ mini" },
          { "name": "Đối tượng thuê:", "content": "Tất cả" },
          { "name": "Gói tin:", "content": "Tin VIP 3" },
          { "name": "Ngày đăng:", "content": "Thứ 6, 15:12 10/05/2024" },
          { "name": "Ngày hết hạn:", "content": "Thứ 4, 15:12 15/05/2024" }
        ]
      },
      "contact": {
        "header": { "header": "Thông tin liên hệ" },
        "content": [
          { "name": "Liên hệ:", "content": "Hồ Đắc Tùng" },
          { "name": "Điện thoại:", "content": "0932029986" },
          { "name": "Zalo", "content": "0932029986" }
        ]
      }
    },
    {
      "images": [
        {
          "img": "https://pt123.cdn.static123.com/images/thumbs/900x600/fit/2024/04/03/15_1712111831.jpg",
          "alt": "Phòng đẹp full nội thất - Nguyễn Tử Nha, P.12 Q. Tân Bình. 0862668827"
        },
        {
          "img": "https://pt123.cdn.static123.com/images/thumbs/900x600/fit/2023/02/22/36df311f-f700-4239-bd7b-1393cb9c8117_1677047849.jpg",
          "alt": "Phòng đẹp full nội thất - Nguyễn Tử Nha, P.12 Q. Tân Bình. 0862668827"
        },
        {
          "img": "https://pt123.cdn.static123.com/images/thumbs/900x600/fit/2024/04/03/14_1712111829.jpg",
          "alt": "Phòng đẹp full nội thất - Nguyễn Tử Nha, P.12 Q. Tân Bình. 0862668827"
        },
        {
          "img": "https://pt123.cdn.static123.com/images/thumbs/900x600/fit/2024/04/03/11_1712111826.jpg",
          "alt": "Phòng đẹp full nội thất - Nguyễn Tử Nha, P.12 Q. Tân Bình. 0862668827"
        },
        {
          "img": "https://pt123.cdn.static123.com/images/thumbs/900x600/fit/2024/04/26/2_1714099573.jpg",
          "alt": "Phòng đẹp full nội thất - Nguyễn Tử Nha, P.12 Q. Tân Bình. 0862668827"
        },
        {
          "img": "https://pt123.cdn.static123.com/images/thumbs/900x600/fit/2024/04/26/4_1714099575.jpg",
          "alt": "Phòng đẹp full nội thất - Nguyễn Tử Nha, P.12 Q. Tân Bình. 0862668827"
        },
        {
          "img": "https://pt123.cdn.static123.com/images/thumbs/900x600/fit/2024/04/03/12_1712111826.jpg",
          "alt": "Phòng đẹp full nội thất - Nguyễn Tử Nha, P.12 Q. Tân Bình. 0862668827"
        },
        {
          "img": "https://pt123.cdn.static123.com/images/thumbs/900x600/fit/2024/04/03/13_1712111828.jpg",
          "alt": "Phòng đẹp full nội thất - Nguyễn Tử Nha, P.12 Q. Tân Bình. 0862668827"
        },
        {
          "img": "https://pt123.cdn.static123.com/images/thumbs/900x600/fit/2024/04/03/15_1712111831.jpg",
          "alt": "Phòng đẹp full nội thất - Nguyễn Tử Nha, P.12 Q. Tân Bình. 0862668827"
        },
        {
          "img": "https://pt123.cdn.static123.com/images/thumbs/900x600/fit/2023/02/22/36df311f-f700-4239-bd7b-1393cb9c8117_1677047849.jpg",
          "alt": "Phòng đẹp full nội thất - Nguyễn Tử Nha, P.12 Q. Tân Bình. 0862668827"
        }
      ],
      "headerDetail": {
        "title": "Phòng đẹp full nội thất - Nguyễn Tử Nha, P.12 Q. Tân Bình. 0862668827",
        "star": "2",
        "class": {
          "content": "Chuyên mục: Cho thuê căn hộ mini Quận Tân Bình",
          "classType": "Cho thuê căn hộ mini Quận Tân Bình"
        },
        "address": "Địa chỉ: Đường Nguyễn Tử Nha, Phường 12, Quận Tân Bình, Hồ Chí Minh",
        "attributes": {
          "price": "5.8 triệu/tháng",
          "acreage": "25m2",
          "published": "Hôm nay",
          "hashtag": "616052"
        }
      },
      "mainContent": {
        "header": { "header": "Thông tin mô tả" },
        "content": [
          "⏩ ⏩ Phòng studio cho thuê đầy đủ nội thất Nguyễn Tử Nha, P.12 Q. Tân Bình.",
          "Giá 4.800.000 - 5.800.000/ tháng. Phí dịch vụ 150k/người. Điện 4k/kwh, nước 100k/người.",
          "Tối đa 2 người/ phòng.",
          "⏩ Thông tin mô tả",
          "- Diện tích: 20 - 25 m2;",
          "- Nhà thiết kế mới, hiện đại, có thang máy, phòng đẹp, sạch sẽ, có ban công, cửa sổ thoáng mát.",
          "- Tiện ích chung: thang máy, Internet Wifi, Camera an ninh, khóa cổng vân tay, giặt sấy.",
          "- Nội thất cao cấp, trang thiết bị hiện đại cao cấp, tiết kiệm điện, trang bị an toàn PCCC.",
          "Vị trí gần ngã giao Trường Chinh - Lý Thường Kiệt, gần các trường Đại Học, bệnh viện lớn.",
          "Đường xá rộng rãi, sạch sẽ, an ninh, vị trí thuận lợi, gần chợ, trường học, nhiều tiện ích xung quanh.",
          "Phù hợp với sinh viên, hộ gia đình nhỏ, nhân viên văn phòng.",
          "Liên hệ - sdt 0903376372 - 0862668827"
        ]
      },
      "overView": {
        "header": { "header": "Đặc điểm tin đăng" },
        "content": [
          { "name": "Mã tin:", "content": "#616052" },
          { "name": "Khu vực", "content": "Cho thuê căn hộ mini Hồ Chí Minh" },
          { "name": "Loại tin rao:", "content": "Cho thuê căn hộ mini" },
          { "name": "Đối tượng thuê:", "content": "Tất cả" },
          { "name": "Gói tin:", "content": "Tin VIP 3" },
          { "name": "Ngày đăng:", "content": "Thứ 6, 08:58 10/05/2024" },
          { "name": "Ngày hết hạn:", "content": "Thứ 2, 15:17 13/05/2024" }
        ]
      },
      "contact": {
        "header": { "header": "Thông tin liên hệ" },
        "content": [
          { "name": "Liên hệ:", "content": "Anh Bảo" },
          { "name": "Điện thoại:", "content": "0903376372" },
          { "name": "Zalo", "content": "0903376372" }
        ]
      }
    },
    {
      "images": [
        {
          "img": "https://pt123.cdn.static123.com/images/thumbs/900x600/fit/2021/06/02/22730163-222604801611350-763240264482296495-n_1622620178.jpg",
          "alt": "Giảm giá sập sàn căn hộ mini giá rẻ, đầy đủ nội thất, quận Bình Thạnh"
        },
        {
          "img": "https://pt123.cdn.static123.com/images/thumbs/900x600/fit/2021/06/02/1_1622620177.jpg",
          "alt": "Giảm giá sập sàn căn hộ mini giá rẻ, đầy đủ nội thất, quận Bình Thạnh"
        },
        {
          "img": "https://pt123.cdn.static123.com/images/thumbs/900x600/fit/2021/06/02/2_1622620176.jpg",
          "alt": "Giảm giá sập sàn căn hộ mini giá rẻ, đầy đủ nội thất, quận Bình Thạnh"
        },
        {
          "img": "https://pt123.cdn.static123.com/images/thumbs/900x600/fit/2021/06/02/3_1622620177.jpg",
          "alt": "Giảm giá sập sàn căn hộ mini giá rẻ, đầy đủ nội thất, quận Bình Thạnh"
        },
        {
          "img": "https://pt123.cdn.static123.com/images/thumbs/900x600/fit/2021/06/02/4_1622620178.jpg",
          "alt": "Giảm giá sập sàn căn hộ mini giá rẻ, đầy đủ nội thất, quận Bình Thạnh"
        },
        {
          "img": "https://pt123.cdn.static123.com/images/thumbs/900x600/fit/2021/06/02/5_1622620178.jpg",
          "alt": "Giảm giá sập sàn căn hộ mini giá rẻ, đầy đủ nội thất, quận Bình Thạnh"
        },
        {
          "img": "https://pt123.cdn.static123.com/images/thumbs/900x600/fit/2021/06/02/22729082-222604804944683-7265275987858501766-n_1622620178.jpg",
          "alt": "Giảm giá sập sàn căn hộ mini giá rẻ, đầy đủ nội thất, quận Bình Thạnh"
        },
        {
          "img": "https://pt123.cdn.static123.com/images/thumbs/900x600/fit/2021/06/02/22730163-222604801611350-763240264482296495-n_1622620178.jpg",
          "alt": "Giảm giá sập sàn căn hộ mini giá rẻ, đầy đủ nội thất, quận Bình Thạnh"
        },
        {
          "img": "https://pt123.cdn.static123.com/images/thumbs/900x600/fit/2021/06/02/1_1622620177.jpg",
          "alt": "Giảm giá sập sàn căn hộ mini giá rẻ, đầy đủ nội thất, quận Bình Thạnh"
        }
      ],
      "headerDetail": {
        "title": "Giảm giá sập sàn căn hộ mini giá rẻ, đầy đủ nội thất, quận Bình Thạnh",
        "star": "2",
        "class": {
          "content": "Chuyên mục: Cho thuê căn hộ mini Quận Bình Thạnh",
          "classType": "Cho thuê căn hộ mini Quận Bình Thạnh"
        },
        "address": "Địa chỉ: 686/66 Đường Xô Viết Nghệ Tĩnh, Phường 26, Quận Bình Thạnh, Hồ Chí Minh",
        "attributes": {
          "price": "4 triệu/tháng",
          "acreage": "25m2",
          "published": "Hôm nay",
          "hashtag": "588414"
        }
      },
      "mainContent": {
        "header": { "header": "Thông tin mô tả" },
        "content": [
          "ƯU ĐÃI CHỈ CÓ DUY NHẤT TẠI ZION",
          "VỊ TRÍ: 685 Xô Viết Nghệ Tĩnh P26 Q.Bình Thạnh",
          "CÔNG VIÊN view sông kế bên.",
          "Cách CHỢ chỉ 200m, phòng GYM cạnh nhà.",
          "Hầm xe RỘNG RÃI, Thang máy SIÊU NHANH.",
          "Cổng vào VÂN TAY quá AN TOÀN.",
          "CÁC TIỆN ÍCH:",
          "1️⃣ Không gian sống như ngôi nhà của bạn: Thoáng mát, sạch sẽ, yên tĩnh.",
          "2️⃣ Có chỗ để xe rộng rãi, sân phơi khô thoáng.",
          "3️⃣ Không còn bị làm phiền.",
          "4️⃣ Không còn lo lắng về an ninh.",
          "5️⃣ Bạn bè được thoải mái đến chơi.",
          "6️⃣ Môi trường sống văn minh, lịch sự, tôn trọng lẫn nhau..",
          "7️⃣ Có bảo vệ coi xe 24/24.",
          "Tiện nghi có sẵn:",
          "️ Không gian có thể trồng cây xanh.",
          "️ Có tủ bếp, tủ quần áo, tủ cá nhân (trang điểm), kệ bếp.",
          "️ Wifi tốc độ cao. Capnet FREE",
          "️ Giường",
          "️ Thang máy.",
          "----------------------------------",
          "- Giặt đồ: Có sẵn máy giặt chung và sân phơi chung.",
          "- Hầm để xe máy có bảo vệ",
          "- Tự do giờ giấc thoải mái",
          "- An ninh: Camera, bảo vệ 24/7, Cảnh sát khu vực thường xuyên kiểm tra. Khu nhà dân trí cao.",
          "------------------------------------------",
          "Cọc 1 tháng. Tiền nhà đóng 1 tháng/lần",
          "Phòng tiêu chuẩn 2ng.",
          "️Thông tin chi tiết LIÊN HỆ:",
          "HOTLINE : 0981796745 ( chủ nhà )"
        ]
      },
      "overView": {
        "header": { "header": "Đặc điểm tin đăng" },
        "content": [
          { "name": "Mã tin:", "content": "#588414" },
          { "name": "Khu vực", "content": "Cho thuê căn hộ mini Hồ Chí Minh" },
          { "name": "Loại tin rao:", "content": "Cho thuê căn hộ mini" },
          { "name": "Đối tượng thuê:", "content": "Tất cả" },
          { "name": "Gói tin:", "content": "Tin VIP 3" },
          { "name": "Ngày đăng:", "content": "Thứ 6, 06:17 10/05/2024" },
          { "name": "Ngày hết hạn:", "content": "Thứ 4, 06:17 15/05/2024" }
        ]
      },
      "contact": {
        "header": { "header": "Thông tin liên hệ" },
        "content": [
          { "name": "Liên hệ:", "content": "TOÀN" },
          { "name": "Điện thoại:", "content": "0981796745" },
          { "name": "Zalo", "content": "0981796745" }
        ]
      }
    },
    {
      "images": [
        {
          "img": "https://pt123.cdn.static123.com/images/thumbs/900x600/fit/2024/04/19/z5341501566859-33e4abdb49ded4d5cbfc1218831c743e_1713519148.jpg",
          "alt": "CĂN HỘ STUDIO MỚI TINH NGAY 250 PHAN TRỌNG TUỆ"
        },
        {
          "img": "https://pt123.cdn.static123.com/images/thumbs/900x600/fit/2024/04/19/z4513068032453-32d148fb0e00c1849c4de77a3385b9f2_1713519135.jpg",
          "alt": "CĂN HỘ STUDIO MỚI TINH NGAY 250 PHAN TRỌNG TUỆ"
        },
        {
          "img": "https://pt123.cdn.static123.com/images/thumbs/900x600/fit/2024/04/19/z5341501515385-d3b3ca7cc95e6d3bb129042d568f74f7_1713519137.jpg",
          "alt": "CĂN HỘ STUDIO MỚI TINH NGAY 250 PHAN TRỌNG TUỆ"
        },
        {
          "img": "https://pt123.cdn.static123.com/images/thumbs/900x600/fit/2024/04/19/z5341501522653-c5f401c9db54e7ece762f30b22099a01_1713519138.jpg",
          "alt": "CĂN HỘ STUDIO MỚI TINH NGAY 250 PHAN TRỌNG TUỆ"
        },
        {
          "img": "https://pt123.cdn.static123.com/images/thumbs/900x600/fit/2024/04/19/z5341501525047-9865749532d5feb1d22967f175fc25f6_1713519142.jpg",
          "alt": "CĂN HỘ STUDIO MỚI TINH NGAY 250 PHAN TRỌNG TUỆ"
        },
        {
          "img": "https://pt123.cdn.static123.com/images/thumbs/900x600/fit/2024/04/19/z5341501532433-8c7ffa11bd7f3caa795167263a98b449_1713519142.jpg",
          "alt": "CĂN HỘ STUDIO MỚI TINH NGAY 250 PHAN TRỌNG TUỆ"
        },
        {
          "img": "https://pt123.cdn.static123.com/images/thumbs/900x600/fit/2024/04/19/z5341501532666-1e8adeaf49cd85ba116b7025eb69c618_1713519144.jpg",
          "alt": "CĂN HỘ STUDIO MỚI TINH NGAY 250 PHAN TRỌNG TUỆ"
        },
        {
          "img": "https://pt123.cdn.static123.com/images/thumbs/900x600/fit/2024/04/19/z5341501546903-4dc6288ddec7a53ef33e7f0f0d902a91_1713519144.jpg",
          "alt": "CĂN HỘ STUDIO MỚI TINH NGAY 250 PHAN TRỌNG TUỆ"
        },
        {
          "img": "https://pt123.cdn.static123.com/images/thumbs/900x600/fit/2024/04/19/z5341501547354-dd894a8aaba35926a839a772a6712848_1713519146.jpg",
          "alt": "CĂN HỘ STUDIO MỚI TINH NGAY 250 PHAN TRỌNG TUỆ"
        },
        {
          "img": "https://pt123.cdn.static123.com/images/thumbs/900x600/fit/2024/04/19/z5341501556404-16b7f999305e85832fc3230856e021e6_1713519146.jpg",
          "alt": "CĂN HỘ STUDIO MỚI TINH NGAY 250 PHAN TRỌNG TUỆ"
        },
        {
          "img": "https://pt123.cdn.static123.com/images/thumbs/900x600/fit/2024/04/19/z5341501556710-5b4462888302b90c97484064e7ed1348_1713519148.jpg",
          "alt": "CĂN HỘ STUDIO MỚI TINH NGAY 250 PHAN TRỌNG TUỆ"
        },
        {
          "img": "https://pt123.cdn.static123.com/images/thumbs/900x600/fit/2024/04/19/z5341501566859-33e4abdb49ded4d5cbfc1218831c743e_1713519148.jpg",
          "alt": "CĂN HỘ STUDIO MỚI TINH NGAY 250 PHAN TRỌNG TUỆ"
        },
        {
          "img": "https://pt123.cdn.static123.com/images/thumbs/900x600/fit/2024/04/19/z4513068032453-32d148fb0e00c1849c4de77a3385b9f2_1713519135.jpg",
          "alt": "CĂN HỘ STUDIO MỚI TINH NGAY 250 PHAN TRỌNG TUỆ"
        }
      ],
      "headerDetail": {
        "title": "CĂN HỘ STUDIO MỚI TINH NGAY 250 PHAN TRỌNG TUỆ",
        "star": "2",
        "class": {
          "content": "Chuyên mục: Cho thuê căn hộ mini Huyện Thanh Trì",
          "classType": "Cho thuê căn hộ mini Huyện Thanh Trì"
        },
        "address": "Địa chỉ: Đường Phan Trọng Tuệ, Xã Thanh Liệt, Huyện Thanh Trì, Hà Nội",
        "attributes": {
          "price": "3.3 triệu/tháng",
          "acreage": "25m2",
          "published": "Hôm nay",
          "hashtag": "652828"
        }
      },
      "mainContent": {
        "header": { "header": "Thông tin mô tả" },
        "content": [
          "Cho thuê căn hộ dịch vụ tại Cầu Tó, Thanh Trì.",
          "Nội thất: Kệ bếp, giường, nệm, tủ lạnh, tủ quần áo, điều hoà, bình nóng lạnh.",
          "Giờ giấc: Tự do, không chung chủ.",
          "Không gian: Rộng rãi, thoáng đãng với tổng diện tích phòng 30m².",
          "Vị trí đắc địa: Xung quanh gần các khu đô thị: KĐT Xa La, KĐT Thanh Hà, KĐT Linh Đàm. Ngoài ra, việc di chuyển đến các bệnh viện K Tân Triều, trung tâm mua sắm và giải trí cũng vô cùng thuận tiện.",
          "An ninh: Văn minh, bảo đảm an toàn cho bạn và gia đình.",
          "Địa chỉ: Cầu Tó, Thanh Trì, Hà Nội."
        ]
      },
      "overView": {
        "header": { "header": "Đặc điểm tin đăng" },
        "content": [
          { "name": "Mã tin:", "content": "#652828" },
          { "name": "Khu vực", "content": "Cho thuê căn hộ mini Hà Nội" },
          { "name": "Loại tin rao:", "content": "Cho thuê căn hộ mini" },
          { "name": "Đối tượng thuê:", "content": "Tất cả" },
          { "name": "Gói tin:", "content": "Tin VIP 3" },
          { "name": "Ngày đăng:", "content": "Thứ 5, 00:12 25/04/2024" },
          { "name": "Ngày hết hạn:", "content": "Thứ 7, 00:12 25/05/2024" }
        ]
      },
      "contact": {
        "header": { "header": "Thông tin liên hệ" },
        "content": [
          { "name": "Liên hệ:", "content": "Ngọc Châu" },
          { "name": "Điện thoại:", "content": "0879240000" },
          { "name": "Zalo", "content": "0879240000" },
          {
            "name": "Facebook",
            "content": "https://www.facebook.com/hlandhouse68"
          }
        ]
      }
    },
    {
      "images": [
        {
          "img": "https://pt123.cdn.static123.com/images/thumbs/900x600/fit/2024/05/13/69f876de553d8ab846c1bed0d1c9c514_1715547229.jpg",
          "alt": "Hệ Thống 999+ Căn hộ cho thuê Quận 3 Đầy đủ các dạng Phòng"
        },
        {
          "img": "https://pt123.cdn.static123.com/images/thumbs/900x600/fit/2024/05/13/1hriisten-975ig6_1715547226.jpg",
          "alt": "Hệ Thống 999+ Căn hộ cho thuê Quận 3 Đầy đủ các dạng Phòng"
        },
        {
          "img": "https://pt123.cdn.static123.com/images/thumbs/900x600/fit/2024/05/13/img-2814_1715547224.jpg",
          "alt": "Hệ Thống 999+ Căn hộ cho thuê Quận 3 Đầy đủ các dạng Phòng"
        },
        {
          "img": "https://pt123.cdn.static123.com/images/thumbs/900x600/fit/2024/05/13/c40138d9f97bf0ed34f4bef3157c8933_1715547220.jpg",
          "alt": "Hệ Thống 999+ Căn hộ cho thuê Quận 3 Đầy đủ các dạng Phòng"
        },
        {
          "img": "https://pt123.cdn.static123.com/images/thumbs/900x600/fit/2024/05/13/4acda0cca8e86d520da19931945ac559_1715547220.jpg",
          "alt": "Hệ Thống 999+ Căn hộ cho thuê Quận 3 Đầy đủ các dạng Phòng"
        },
        {
          "img": "https://pt123.cdn.static123.com/images/thumbs/900x600/fit/2024/05/13/94811fb1f2feb642b2acd62b52bb85f2_1715547227.jpg",
          "alt": "Hệ Thống 999+ Căn hộ cho thuê Quận 3 Đầy đủ các dạng Phòng"
        },
        {
          "img": "https://pt123.cdn.static123.com/images/thumbs/900x600/fit/2024/05/13/5b791316301bea97610b5721645861e6_1715547221.jpg",
          "alt": "Hệ Thống 999+ Căn hộ cho thuê Quận 3 Đầy đủ các dạng Phòng"
        },
        {
          "img": "https://pt123.cdn.static123.com/images/thumbs/900x600/fit/2024/05/13/9d87b89e164df774546d715d0479ce45_1715547222.jpg",
          "alt": "Hệ Thống 999+ Căn hộ cho thuê Quận 3 Đầy đủ các dạng Phòng"
        },
        {
          "img": "https://pt123.cdn.static123.com/images/thumbs/900x600/fit/2024/05/13/1hsutknb6-94g885_1715547226.jpg",
          "alt": "Hệ Thống 999+ Căn hộ cho thuê Quận 3 Đầy đủ các dạng Phòng"
        },
        {
          "img": "https://pt123.cdn.static123.com/images/thumbs/900x600/fit/2024/05/13/29038b81e8b855e32147ec09c1f7cadc_1715547224.jpg",
          "alt": "Hệ Thống 999+ Căn hộ cho thuê Quận 3 Đầy đủ các dạng Phòng"
        },
        {
          "img": "https://pt123.cdn.static123.com/images/thumbs/900x600/fit/2024/05/13/9f8da2b6bf8c2840582f60dcbb4e6852_1715547227.jpg",
          "alt": "Hệ Thống 999+ Căn hộ cho thuê Quận 3 Đầy đủ các dạng Phòng"
        },
        {
          "img": "https://pt123.cdn.static123.com/images/thumbs/900x600/fit/2024/05/13/1ae9c14cc096d290b5c811727f9597ef_1715547227.jpg",
          "alt": "Hệ Thống 999+ Căn hộ cho thuê Quận 3 Đầy đủ các dạng Phòng"
        },
        {
          "img": "https://pt123.cdn.static123.com/images/thumbs/900x600/fit/2024/05/13/430e77d13273fb16524033fa7104c02b_1715547227.jpg",
          "alt": "Hệ Thống 999+ Căn hộ cho thuê Quận 3 Đầy đủ các dạng Phòng"
        },
        {
          "img": "https://pt123.cdn.static123.com/images/thumbs/900x600/fit/2024/05/13/9950c7819745e150aa0f00038b7f8b8d_1715547227.jpg",
          "alt": "Hệ Thống 999+ Căn hộ cho thuê Quận 3 Đầy đủ các dạng Phòng"
        },
        {
          "img": "https://pt123.cdn.static123.com/images/thumbs/900x600/fit/2024/05/13/74ec6780525de775311691558fb52a87_1715547229.jpg",
          "alt": "Hệ Thống 999+ Căn hộ cho thuê Quận 3 Đầy đủ các dạng Phòng"
        },
        {
          "img": "https://pt123.cdn.static123.com/images/thumbs/900x600/fit/2024/05/13/69f876de553d8ab846c1bed0d1c9c514_1715547229.jpg",
          "alt": "Hệ Thống 999+ Căn hộ cho thuê Quận 3 Đầy đủ các dạng Phòng"
        },
        {
          "img": "https://pt123.cdn.static123.com/images/thumbs/900x600/fit/2024/05/13/1hriisten-975ig6_1715547226.jpg",
          "alt": "Hệ Thống 999+ Căn hộ cho thuê Quận 3 Đầy đủ các dạng Phòng"
        }
      ],
      "headerDetail": {
        "title": "Hệ Thống 999+ Căn hộ cho thuê Quận 3 Đầy đủ các dạng Phòng",
        "class": {
          "content": "Chuyên mục: Cho thuê căn hộ dịch vụ Quận 3",
          "classType": "Cho thuê căn hộ dịch vụ Quận 3"
        },
        "address": "Địa chỉ: Hoàng Sa, Phường 6, Quận 3, Hồ Chí Minh",
        "attributes": {
          "price": "6 triệu/tháng",
          "acreage": "40m2",
          "published": "8 giờ trước",
          "hashtag": "654584"
        }
      },
      "mainContent": {
        "header": { "header": "Thông tin mô tả" },
        "content": [
          "Chuyên cho thuê căn hộ mini/căn hộ dịch vụ/căn hộ cao cấp Q1,3,10 TPHCM",
          "Dạng Studio (bếp ko tách riêng): Giá từ 5tr/tháng",
          "Dạng 1PN riêng (bếp tách riêng pn) Chỉ từ 7tr/tháng",
          "Dạng 2PN riêng (Phòng bếp +2pn) Chỉ từ 9tr/tháng",
          "Hệ thống căn hộ trải đủ các cung đường: Cách Mạng Tháng Tám, Lý Chính Thắng, Hai Bà Trưng, Nam Kỳ KHởi Nghĩa, Lê Văn Sỹ, Võ Văn Tần, Trương ĐỊnh,...",
          "Gần các địa điểm nổi tiếng: Hồ con Rùa, Siêu thị, Cầu Công Lý, ...",
          "Add Zalo 0866.739.846 để được tư vấn và nhận cập nhập các sản phẩm hót - giá tốt mỗi ngày️"
        ]
      },
      "overView": {
        "header": { "header": "Đặc điểm tin đăng" },
        "content": [
          { "name": "Mã tin:", "content": "#654584" },
          {
            "name": "Khu vực",
            "content": "Cho thuê căn hộ dịch vụ Hồ Chí Minh"
          },
          { "name": "Loại tin rao:", "content": "Cho thuê căn hộ dịch vụ" },
          { "name": "Đối tượng thuê:", "content": "Tất cả" },
          { "name": "Gói tin:", "content": "Tin miễn phí" },
          { "name": "Ngày đăng:", "content": "Thứ 2, 03:54 13/05/2024" },
          { "name": "Ngày hết hạn:", "content": "Thứ 7, 03:54 18/05/2024" }
        ]
      },
      "contact": {
        "header": { "header": "Thông tin liên hệ" },
        "content": [
          { "name": "Liên hệ:", "content": "nguyen tien phong" },
          { "name": "Điện thoại:", "content": "0866739846" },
          { "name": "Zalo", "content": "0866739846" }
        ]
      }
    },
    {
      "images": [
        {
          "img": "https://pt123.cdn.static123.com/images/thumbs/900x600/fit/2024/05/13/29d3b0658ad15ad1469f18ffa7df7c75_1715546514.jpg",
          "alt": "Cho thuê Studio Bancon lớn Nguyễn Trãi Q1 Full Nội Thất"
        },
        {
          "img": "https://pt123.cdn.static123.com/images/thumbs/900x600/fit/2024/05/13/8d7c6c4fbbcb209f83d2df5b37731f89_1715546510.jpg",
          "alt": "Cho thuê Studio Bancon lớn Nguyễn Trãi Q1 Full Nội Thất"
        },
        {
          "img": "https://pt123.cdn.static123.com/images/thumbs/900x600/fit/2024/05/13/e2bc08a3dc954724f0a6d14b77fa1cf0_1715546510.jpg",
          "alt": "Cho thuê Studio Bancon lớn Nguyễn Trãi Q1 Full Nội Thất"
        },
        {
          "img": "https://pt123.cdn.static123.com/images/thumbs/900x600/fit/2024/05/13/a131f2515504e4483d2d634cc0a0bd06_1715546512.jpg",
          "alt": "Cho thuê Studio Bancon lớn Nguyễn Trãi Q1 Full Nội Thất"
        },
        {
          "img": "https://pt123.cdn.static123.com/images/thumbs/900x600/fit/2024/05/13/3f59705594798cd96e8beb11546752fb_1715546512.jpg",
          "alt": "Cho thuê Studio Bancon lớn Nguyễn Trãi Q1 Full Nội Thất"
        },
        {
          "img": "https://pt123.cdn.static123.com/images/thumbs/900x600/fit/2024/05/13/132397cd07f611bacb758be67601b962_1715546514.jpg",
          "alt": "Cho thuê Studio Bancon lớn Nguyễn Trãi Q1 Full Nội Thất"
        },
        {
          "img": "https://pt123.cdn.static123.com/images/thumbs/900x600/fit/2024/05/13/29d3b0658ad15ad1469f18ffa7df7c75_1715546514.jpg",
          "alt": "Cho thuê Studio Bancon lớn Nguyễn Trãi Q1 Full Nội Thất"
        },
        {
          "img": "https://pt123.cdn.static123.com/images/thumbs/900x600/fit/2024/05/13/8d7c6c4fbbcb209f83d2df5b37731f89_1715546510.jpg",
          "alt": "Cho thuê Studio Bancon lớn Nguyễn Trãi Q1 Full Nội Thất"
        }
      ],
      "headerDetail": {
        "title": "Cho thuê Studio Bancon lớn Nguyễn Trãi Q1 Full Nội Thất",
        "class": {
          "content": "Chuyên mục: Cho thuê căn hộ dịch vụ Quận 1",
          "classType": "Cho thuê căn hộ dịch vụ Quận 1"
        },
        "address": "Địa chỉ: Nguyễn Trãi, Phường Nguyễn Cư Trinh, Quận 1, Hồ Chí Minh",
        "attributes": {
          "price": "7.2 triệu/tháng",
          "acreage": "40m2",
          "published": "8 giờ trước",
          "hashtag": "654583"
        }
      },
      "mainContent": {
        "header": { "header": "Thông tin mô tả" },
        "content": [
          "Cho thuê Studio Bancon lớn Nguyễn Trãi Q1 Full Nội Thất",
          "̣ ́: Nguyễn Trãi Quận 1",
          "Gần Bùi viện",
          "Gần Bitexco",
          "Phố đi bộ",
          "Máy giặt riêng, được nuôi thú cưng",
          "An ninh, camera an ninh 24/24, khóa vân tay",
          "Vị trí để xe rộng rãi",
          "Xe free",
          "-̛ Đ̃ ́ ̂ ̂ ̀ -",
          "_____________________________",
          "⌨️ Hotline : 0866739846",
          "Call, Zalo..."
        ]
      },
      "overView": {
        "header": { "header": "Đặc điểm tin đăng" },
        "content": [
          { "name": "Mã tin:", "content": "#654583" },
          {
            "name": "Khu vực",
            "content": "Cho thuê căn hộ dịch vụ Hồ Chí Minh"
          },
          { "name": "Loại tin rao:", "content": "Cho thuê căn hộ dịch vụ" },
          { "name": "Đối tượng thuê:", "content": "Tất cả" },
          { "name": "Gói tin:", "content": "Tin miễn phí" },
          { "name": "Ngày đăng:", "content": "Thứ 2, 03:44 13/05/2024" },
          { "name": "Ngày hết hạn:", "content": "Thứ 7, 03:44 18/05/2024" }
        ]
      },
      "contact": {
        "header": { "header": "Thông tin liên hệ" },
        "content": [
          { "name": "Liên hệ:", "content": "nguyen tien phong" },
          { "name": "Điện thoại:", "content": "0866739846" },
          { "name": "Zalo", "content": "0866739846" }
        ]
      }
    },
    {
      "images": [
        {
          "img": "https://pt123.cdn.static123.com/images/thumbs/900x600/fit/2024/05/07/438332802-6872790972823106-1375065521496301290-n_1715020207.jpg",
          "alt": "siêu phẩm GIÁ CỰC RẺ PHÒNG CỰC CHILL NGAY CÔNG VIÊN HOÀNG VĂN THỤ P4 TÂN BÌNH"
        },
        {
          "img": "https://pt123.cdn.static123.com/images/thumbs/900x600/fit/2024/05/07/438112372-809513420595537-7359180639575560324-n_1715020204.jpg",
          "alt": "siêu phẩm GIÁ CỰC RẺ PHÒNG CỰC CHILL NGAY CÔNG VIÊN HOÀNG VĂN THỤ P4 TÂN BÌNH"
        },
        {
          "img": "https://pt123.cdn.static123.com/images/thumbs/900x600/fit/2024/05/07/438115920-1148791869647174-9087557097786901626-n_1715020204.jpg",
          "alt": "siêu phẩm GIÁ CỰC RẺ PHÒNG CỰC CHILL NGAY CÔNG VIÊN HOÀNG VĂN THỤ P4 TÂN BÌNH"
        },
        {
          "img": "https://pt123.cdn.static123.com/images/thumbs/900x600/fit/2024/05/07/438158213-976508574029808-2866432267880266012-n_1715020207.jpg",
          "alt": "siêu phẩm GIÁ CỰC RẺ PHÒNG CỰC CHILL NGAY CÔNG VIÊN HOÀNG VĂN THỤ P4 TÂN BÌNH"
        },
        {
          "img": "https://pt123.cdn.static123.com/images/thumbs/900x600/fit/2024/05/07/438125060-824444159543437-8214198782601529995-n_1715020206.jpg",
          "alt": "siêu phẩm GIÁ CỰC RẺ PHÒNG CỰC CHILL NGAY CÔNG VIÊN HOÀNG VĂN THỤ P4 TÂN BÌNH"
        },
        {
          "img": "https://pt123.cdn.static123.com/images/thumbs/900x600/fit/2024/05/07/438125152-7414074302031624-6281990754172190769-n_1715020206.jpg",
          "alt": "siêu phẩm GIÁ CỰC RẺ PHÒNG CỰC CHILL NGAY CÔNG VIÊN HOÀNG VĂN THỤ P4 TÂN BÌNH"
        },
        {
          "img": "https://pt123.cdn.static123.com/images/thumbs/900x600/fit/2024/05/07/438332802-6872790972823106-1375065521496301290-n_1715020207.jpg",
          "alt": "siêu phẩm GIÁ CỰC RẺ PHÒNG CỰC CHILL NGAY CÔNG VIÊN HOÀNG VĂN THỤ P4 TÂN BÌNH"
        },
        {
          "img": "https://pt123.cdn.static123.com/images/thumbs/900x600/fit/2024/05/07/438112372-809513420595537-7359180639575560324-n_1715020204.jpg",
          "alt": "siêu phẩm GIÁ CỰC RẺ PHÒNG CỰC CHILL NGAY CÔNG VIÊN HOÀNG VĂN THỤ P4 TÂN BÌNH"
        }
      ],
      "headerDetail": {
        "title": "siêu phẩm GIÁ CỰC RẺ PHÒNG CỰC CHILL NGAY CÔNG VIÊN HOÀNG VĂN THỤ P4 TÂN BÌNH",
        "class": {
          "content": "Chuyên mục: Cho thuê căn hộ dịch vụ Quận Tân Bình",
          "classType": "Cho thuê căn hộ dịch vụ Quận Tân Bình"
        },
        "address": "Địa chỉ: Hoàng Văn Thụ, Phường 4, Quận Tân Bình, Hồ Chí Minh",
        "attributes": {
          "price": "7.5 triệu/tháng",
          "acreage": "65m2",
          "published": "11 giờ trước",
          "hashtag": "646180"
        }
      },
      "mainContent": {
        "header": { "header": "Thông tin mô tả" },
        "content": [
          "Vị Trí căn hộ: Đường HOÀNG VĂN THỤ P4 Quận Tân Bình",
          "Giá chỉ từ 4.000.000Đ - 4.500.000Đ - 5.000.000Đ",
          "- ĐA DẠNG CÁC LOẠI PHÒNG ỐC THEO Ý CỦA KHÁCH HÀNG",
          "- VỚI GIÁ CẢ HỢP LÝ, HỖ TRỢ KHÁCH NHIỆT TÌNH...",
          "- HỆ THỐNG PCCC ĐÃ ĐƯỢC KIỂM DUYỆT",
          "- AN NINH CHẤT LƯỢNG DỊCH VỤ TỐT",
          "- Vị trí gần trục đường lớn NGÃ TƯ BẢY HIỀN, LĂNG CHA CẢ, LÊ VĂN SỸ, HOÀNG VĂN THỤ, SÂN BAY TÂN SƠN NHẤT..",
          "- Tiện di chuyển qua các quận 1, quận 3, quận10, quận 5, quận 4",
          "Tổng quan :",
          "- Nội Thất Đầy Đủ: Tủ Lạnh, Máy Lạnh, Máy Giặt, Máy Nóng Lạnh, Lò Vi Sóng, Bếp Điện, Bộ Sofa, Bàn Ghế, Nệm, Kệ Tủ….",
          "- Căn hộ studio có ban công, cửa sổ thoáng đầy đủ tiện nghi",
          "- Ra vào bằng vân tay, giờ giấc tự do, Camera 24/7",
          "• Full nội thất, xách vali vào ở thôi",
          "• Hầm xe rộng, Ra vào vân tay",
          "• Camera an ninh cao, yên tĩnh",
          "• Giờ giấc tự do, Không chung chủ",
          "• Giặt sấy Riêng",
          "Chi phí bao gồm",
          "- Điện",
          "- Nước",
          "- Phí dịch vụ"
        ]
      },
      "overView": {
        "header": { "header": "Đặc điểm tin đăng" },
        "content": [
          { "name": "Mã tin:", "content": "#646180" },
          {
            "name": "Khu vực",
            "content": "Cho thuê căn hộ dịch vụ Hồ Chí Minh"
          },
          { "name": "Loại tin rao:", "content": "Cho thuê căn hộ dịch vụ" },
          { "name": "Đối tượng thuê:", "content": "Tất cả" },
          { "name": "Gói tin:", "content": "Tin thường" },
          { "name": "Ngày đăng:", "content": "Thứ 2, 01:26 13/05/2024" },
          { "name": "Ngày hết hạn:", "content": "Thứ 7, 01:26 18/05/2024" }
        ]
      },
      "contact": {
        "header": { "header": "Thông tin liên hệ" },
        "content": [
          { "name": "Liên hệ:", "content": "Nguyễn Minh Trực" },
          { "name": "Điện thoại:", "content": "0797787910" },
          { "name": "Zalo", "content": "0797787910" }
        ]
      }
    },
    {
      "images": [
        {
          "img": "https://pt123.cdn.static123.com/images/thumbs/900x600/fit/2024/04/27/435785603-2275985116070318-692206047102116124-n_1714156364.jpg",
          "alt": "siêu phẩm MỚI THOÁNG ĐẸP SIÊU RẺ ĐẦY ĐỦ TIỆN NGHI ngay TRUNG TÂM Q6"
        },
        {
          "img": "https://pt123.cdn.static123.com/images/thumbs/900x600/fit/2024/04/27/438124799-942569630884557-7598555524273185981-n_1714156365.jpg",
          "alt": "siêu phẩm MỚI THOÁNG ĐẸP SIÊU RẺ ĐẦY ĐỦ TIỆN NGHI ngay TRUNG TÂM Q6"
        },
        {
          "img": "https://pt123.cdn.static123.com/images/thumbs/900x600/fit/2024/04/27/438083488-452463234003339-8730918592645668856-n_1714156365.jpg",
          "alt": "siêu phẩm MỚI THOÁNG ĐẸP SIÊU RẺ ĐẦY ĐỦ TIỆN NGHI ngay TRUNG TÂM Q6"
        },
        {
          "img": "https://pt123.cdn.static123.com/images/thumbs/900x600/fit/2024/04/27/438083330-1521778438687301-9108154166384026229-n_1714156364.jpg",
          "alt": "siêu phẩm MỚI THOÁNG ĐẸP SIÊU RẺ ĐẦY ĐỦ TIỆN NGHI ngay TRUNG TÂM Q6"
        },
        {
          "img": "https://pt123.cdn.static123.com/images/thumbs/900x600/fit/2024/04/27/438051584-1703901763685364-8989471359897823101-n_1714156364.jpg",
          "alt": "siêu phẩm MỚI THOÁNG ĐẸP SIÊU RẺ ĐẦY ĐỦ TIỆN NGHI ngay TRUNG TÂM Q6"
        },
        {
          "img": "https://pt123.cdn.static123.com/images/thumbs/900x600/fit/2024/04/27/435785603-2275985116070318-692206047102116124-n_1714156364.jpg",
          "alt": "siêu phẩm MỚI THOÁNG ĐẸP SIÊU RẺ ĐẦY ĐỦ TIỆN NGHI ngay TRUNG TÂM Q6"
        },
        {
          "img": "https://pt123.cdn.static123.com/images/thumbs/900x600/fit/2024/04/27/438124799-942569630884557-7598555524273185981-n_1714156365.jpg",
          "alt": "siêu phẩm MỚI THOÁNG ĐẸP SIÊU RẺ ĐẦY ĐỦ TIỆN NGHI ngay TRUNG TÂM Q6"
        }
      ],
      "headerDetail": {
        "title": "siêu phẩm MỚI THOÁNG ĐẸP SIÊU RẺ ĐẦY ĐỦ TIỆN NGHI ngay TRUNG TÂM Q6",
        "class": {
          "content": "Chuyên mục: Cho thuê căn hộ dịch vụ Quận 6",
          "classType": "Cho thuê căn hộ dịch vụ Quận 6"
        },
        "address": "Địa chỉ: Đường Hậu Giang, Phường 9, Quận 6, Hồ Chí Minh",
        "attributes": {
          "price": "5.4 triệu/tháng",
          "acreage": "50m2",
          "published": "11 giờ trước",
          "hashtag": "629497"
        }
      },
      "mainContent": {
        "header": { "header": "Thông tin mô tả" },
        "content": [
          "căn hộ CAO CẤP FULL NỘI THẤT bancol ngay Hậu Giang, Nguyễn Văn Luông",
          "CĂN HỘ DẠNG STUDIO 1PN 2PN FULL NỘI THẤT GIÁ SIÊU RẺ ngay Hậu Giang, Nguyễn Văn Luông, Hồng Bàng giáp trung tâm",
          "QUẬN TRUNG TÂM 5 PHÚT",
          "MỚI 100% - ƯU ĐÃI GIẢM 500K (tư vấn nhiệt tình thân thiện)",
          "AN NINH & TIỆN NGHI & TIẾT KIỆM & THOÁT MÁT",
          "Nội thất mới hoàn toàn thì tại sao không thuê!",
          "Nhanh tay ib, call để biết thêm chi tiết nhé.",
          "Call or Zalo: MINH TRỰC MEGAs"
        ]
      },
      "overView": {
        "header": { "header": "Đặc điểm tin đăng" },
        "content": [
          { "name": "Mã tin:", "content": "#629497" },
          {
            "name": "Khu vực",
            "content": "Cho thuê căn hộ dịch vụ Hồ Chí Minh"
          },
          { "name": "Loại tin rao:", "content": "Cho thuê căn hộ dịch vụ" },
          { "name": "Đối tượng thuê:", "content": "Tất cả" },
          { "name": "Gói tin:", "content": "Tin thường" },
          { "name": "Ngày đăng:", "content": "Thứ 2, 01:26 13/05/2024" },
          { "name": "Ngày hết hạn:", "content": "Thứ 7, 01:26 18/05/2024" }
        ]
      },
      "contact": {
        "header": { "header": "Thông tin liên hệ" },
        "content": [
          { "name": "Liên hệ:", "content": "Nguyễn Minh Trực" },
          { "name": "Điện thoại:", "content": "0797787910" },
          { "name": "Zalo", "content": "0797787910" }
        ]
      }
    },
    {
      "images": [
        {
          "img": "https://pt123.cdn.static123.com/images/thumbs/900x600/fit/2023/09/09/z4607282052923-f01cc4a7ae7a9e1ecb0284f2726ab63b_1694203453.jpg",
          "alt": "Căn hộ cao cấp dạng studio 1PN siêu rẻ ngay Khu Sân Bay TSN"
        },
        {
          "img": "https://pt123.cdn.static123.com/images/thumbs/900x600/fit/2023/09/09/z4607282052532-3abf83840785c3c87e89d923cf24c1c7_1694203451.jpg",
          "alt": "Căn hộ cao cấp dạng studio 1PN siêu rẻ ngay Khu Sân Bay TSN"
        },
        {
          "img": "https://pt123.cdn.static123.com/images/thumbs/900x600/fit/2023/09/09/z4607282051407-971ecd846dce86b92eea61e62314b39e_1694203447.jpg",
          "alt": "Căn hộ cao cấp dạng studio 1PN siêu rẻ ngay Khu Sân Bay TSN"
        },
        {
          "img": "https://pt123.cdn.static123.com/images/thumbs/900x600/fit/2023/09/09/z4607282051631-51401a2684180a67f624b06e7b3df651_1694203447.jpg",
          "alt": "Căn hộ cao cấp dạng studio 1PN siêu rẻ ngay Khu Sân Bay TSN"
        },
        {
          "img": "https://pt123.cdn.static123.com/images/thumbs/900x600/fit/2023/09/09/z4607282051871-7dc47362b429a5e859b7dde98481b3e5_1694203449.jpg",
          "alt": "Căn hộ cao cấp dạng studio 1PN siêu rẻ ngay Khu Sân Bay TSN"
        },
        {
          "img": "https://pt123.cdn.static123.com/images/thumbs/900x600/fit/2023/09/09/z4607282052083-b618f96110571a1530dc96ce549cfd31_1694203449.jpg",
          "alt": "Căn hộ cao cấp dạng studio 1PN siêu rẻ ngay Khu Sân Bay TSN"
        },
        {
          "img": "https://pt123.cdn.static123.com/images/thumbs/900x600/fit/2023/09/09/z4607282052152-dc9bbe11036d72fe01c22a048ee6dcf7_1694203451.jpg",
          "alt": "Căn hộ cao cấp dạng studio 1PN siêu rẻ ngay Khu Sân Bay TSN"
        },
        {
          "img": "https://pt123.cdn.static123.com/images/thumbs/900x600/fit/2023/09/09/z4607282052784-4aa94836b29150197cb184b6f0fa6b11_1694203453.jpg",
          "alt": "Căn hộ cao cấp dạng studio 1PN siêu rẻ ngay Khu Sân Bay TSN"
        },
        {
          "img": "https://pt123.cdn.static123.com/images/thumbs/900x600/fit/2023/09/09/z4607282052923-f01cc4a7ae7a9e1ecb0284f2726ab63b_1694203453.jpg",
          "alt": "Căn hộ cao cấp dạng studio 1PN siêu rẻ ngay Khu Sân Bay TSN"
        },
        {
          "img": "https://pt123.cdn.static123.com/images/thumbs/900x600/fit/2023/09/09/z4607282052532-3abf83840785c3c87e89d923cf24c1c7_1694203451.jpg",
          "alt": "Căn hộ cao cấp dạng studio 1PN siêu rẻ ngay Khu Sân Bay TSN"
        }
      ],
      "headerDetail": {
        "title": "Căn hộ cao cấp dạng studio 1PN siêu rẻ ngay Khu Sân Bay TSN",
        "class": {
          "content": "Chuyên mục: Cho thuê căn hộ dịch vụ Quận Tân Bình",
          "classType": "Cho thuê căn hộ dịch vụ Quận Tân Bình"
        },
        "address": "Địa chỉ: Đường Trường Sơn, Phường 2, Quận Tân Bình, Hồ Chí Minh",
        "attributes": {
          "price": "5 triệu/tháng",
          "acreage": "40m2",
          "published": "11 giờ trước",
          "hashtag": "634958"
        }
      },
      "mainContent": {
        "header": { "header": "Thông tin mô tả" },
        "content": [
          "CĂN HỘ DẠNG STUDIO 1PN 2PN FULL NỘI THẤT GIÁ SIÊU RẺ tại Bạch Đằng, Trường Sơn, Phổ Quang Tân Bình",
          "Địa chỉ: Bạch Đằng, Trường Sơn, Phổ Quang, Quận Tân Bình, TP. Hồ Chí Minh",
          "Giá thuê: ƯU ĐÃI GIẢM 500K - Tư vấn nhiệt tình thân thiện",
          "Tiện ích:",
          "Mới 100%",
          "Vị trí trung tâm, chỉ cách quận trung tâm 5 phút",
          "An ninh đảm bảo",
          "Nội thất mới hoàn toàn",
          "Tiết kiệm và thoát mát",
          "Liên hệ:",
          "Gọi hoặc Zalo: MINH TRỰC MEGAS"
        ]
      },
      "overView": {
        "header": { "header": "Đặc điểm tin đăng" },
        "content": [
          { "name": "Mã tin:", "content": "#634958" },
          {
            "name": "Khu vực",
            "content": "Cho thuê căn hộ dịch vụ Hồ Chí Minh"
          },
          { "name": "Loại tin rao:", "content": "Cho thuê căn hộ dịch vụ" },
          { "name": "Đối tượng thuê:", "content": "Tất cả" },
          { "name": "Gói tin:", "content": "Tin thường" },
          { "name": "Ngày đăng:", "content": "Thứ 2, 01:25 13/05/2024" },
          { "name": "Ngày hết hạn:", "content": "Thứ 7, 01:25 18/05/2024" }
        ]
      },
      "contact": {
        "header": { "header": "Thông tin liên hệ" },
        "content": [
          { "name": "Liên hệ:", "content": "Nguyễn Minh Trực" },
          { "name": "Điện thoại:", "content": "0797787910" },
          { "name": "Zalo", "content": "0797787910" }
        ]
      }
    },
    {
      "images": [
        {
          "img": "https://pt123.cdn.static123.com/images/thumbs/900x600/fit/2024/04/16/z4238492574105-7db4ea8aa7e178dce701b6bf70160220_1713210348.jpg",
          "alt": "Căn hộ MỚI FULL NỘI THẤT GIÁ SIÊU RẺ AN NINH TIỆN NGHI ngay Lý Thái Tổ"
        },
        {
          "img": "https://pt123.cdn.static123.com/images/thumbs/900x600/fit/2024/04/16/z4238492568871-fc2dd15584669615310e00001e5528b6_1713210344.jpg",
          "alt": "Căn hộ MỚI FULL NỘI THẤT GIÁ SIÊU RẺ AN NINH TIỆN NGHI ngay Lý Thái Tổ"
        },
        {
          "img": "https://pt123.cdn.static123.com/images/thumbs/900x600/fit/2024/04/16/z4238492567882-db9c3d1d73f584eb49dd248cb3270dbd_1713210342.jpg",
          "alt": "Căn hộ MỚI FULL NỘI THẤT GIÁ SIÊU RẺ AN NINH TIỆN NGHI ngay Lý Thái Tổ"
        },
        {
          "img": "https://pt123.cdn.static123.com/images/thumbs/900x600/fit/2024/04/16/z4238492568451-7b977f872a757c7019b342cf0b7fbde2_1713210342.jpg",
          "alt": "Căn hộ MỚI FULL NỘI THẤT GIÁ SIÊU RẺ AN NINH TIỆN NGHI ngay Lý Thái Tổ"
        },
        {
          "img": "https://pt123.cdn.static123.com/images/thumbs/900x600/fit/2024/04/16/z4238492568863-e35a18c070653c466a7813d982f47c18_1713210343.jpg",
          "alt": "Căn hộ MỚI FULL NỘI THẤT GIÁ SIÊU RẺ AN NINH TIỆN NGHI ngay Lý Thái Tổ"
        },
        {
          "img": "https://pt123.cdn.static123.com/images/thumbs/900x600/fit/2024/04/16/z4238492569370-ffaa7acec4faad1dbd5258e4c29c22c3_1713210345.jpg",
          "alt": "Căn hộ MỚI FULL NỘI THẤT GIÁ SIÊU RẺ AN NINH TIỆN NGHI ngay Lý Thái Tổ"
        },
        {
          "img": "https://pt123.cdn.static123.com/images/thumbs/900x600/fit/2024/04/16/z4238492570010-040d8db226bea6d5e3ae0c7c01649b1e_1713210346.jpg",
          "alt": "Căn hộ MỚI FULL NỘI THẤT GIÁ SIÊU RẺ AN NINH TIỆN NGHI ngay Lý Thái Tổ"
        },
        {
          "img": "https://pt123.cdn.static123.com/images/thumbs/900x600/fit/2024/04/16/z4238492570628-6ee5401d091659731dd0626af487e3fb_1713210348.jpg",
          "alt": "Căn hộ MỚI FULL NỘI THẤT GIÁ SIÊU RẺ AN NINH TIỆN NGHI ngay Lý Thái Tổ"
        },
        {
          "img": "https://pt123.cdn.static123.com/images/thumbs/900x600/fit/2024/04/16/z4238492574105-7db4ea8aa7e178dce701b6bf70160220_1713210348.jpg",
          "alt": "Căn hộ MỚI FULL NỘI THẤT GIÁ SIÊU RẺ AN NINH TIỆN NGHI ngay Lý Thái Tổ"
        },
        {
          "img": "https://pt123.cdn.static123.com/images/thumbs/900x600/fit/2024/04/16/z4238492568871-fc2dd15584669615310e00001e5528b6_1713210344.jpg",
          "alt": "Căn hộ MỚI FULL NỘI THẤT GIÁ SIÊU RẺ AN NINH TIỆN NGHI ngay Lý Thái Tổ"
        }
      ],
      "headerDetail": {
        "title": "Căn hộ MỚI FULL NỘI THẤT GIÁ SIÊU RẺ AN NINH TIỆN NGHI ngay Lý Thái Tổ",
        "class": {
          "content": "Chuyên mục: Cho thuê căn hộ dịch vụ Quận 10",
          "classType": "Cho thuê căn hộ dịch vụ Quận 10"
        },
        "address": "Địa chỉ: Đường Cách Mạng Tháng Tám, Phường 13, Quận 10, Hồ Chí Minh",
        "attributes": {
          "price": "5.1 triệu/tháng",
          "acreage": "45m2",
          "published": "11 giờ trước",
          "hashtag": "635583"
        }
      },
      "mainContent": {
        "header": { "header": "Thông tin mô tả" },
        "content": [
          "Vị Trí căn hộ: Đường Lý Thái Tổ , Phường 1 Quận 10",
          "Giá chỉ từ 5.000.000Đ - 6.000.000Đ - 8.300.000Đ",
          "- ĐA DẠNG CÁC LOẠI PHÒNG ỐC THEO Ý CỦA KHÁCH HÀNG",
          "- VỚI GIÁ CẢ HỢP LÝ, HỖ TRỢ KHÁCH NHIỆT TÌNH...",
          "- HỆ THỐNG PCCC ĐÃ ĐƯỢC KIỂM DUYỆT",
          "- AN NINH CHẤT LƯỢNG DỊCH VỤ TỐT",
          "- Vị trí gần trục đường lớn Cách Mạng Tháng Tám, Cống Quỳnh, Trần Hưng Đạo, Nguyễn Cư Trinh, Nguyễn Trãi.",
          "- Tiện di chuyển qua các quận 1, quận 3, quận10, quận 5, quận 4",
          "Tổng quan :",
          "- Nội Thất Đầy Đủ: Tủ Lạnh, Máy Lạnh, Máy Giặt, Máy Nóng Lạnh, Lò Vi Sóng, Bếp Điện, Bộ Sofa, Bàn Ghế, Nệm, Kệ Tủ….",
          "- Căn hộ studio có ban công, cửa sổ thoáng đầy đủ tiện nghi",
          "- Ra vào bằng vân tay, giờ giấc tự do, Camera 24/7",
          "• Full nội thất, xách vali vào ở thôi",
          "• Hầm xe rộng, Ra vào vân tay",
          "• Camera an ninh cao, yên tĩnh",
          "• Giờ giấc tự do, Không chung chủ",
          "• Giặt sấy Riêng",
          "Chi phí bao gồm",
          "- Điện",
          "- Nước",
          "- Phí dịch vụ"
        ]
      },
      "overView": {
        "header": { "header": "Đặc điểm tin đăng" },
        "content": [
          { "name": "Mã tin:", "content": "#635583" },
          {
            "name": "Khu vực",
            "content": "Cho thuê căn hộ dịch vụ Hồ Chí Minh"
          },
          { "name": "Loại tin rao:", "content": "Cho thuê căn hộ dịch vụ" },
          { "name": "Đối tượng thuê:", "content": "Tất cả" },
          { "name": "Gói tin:", "content": "Tin thường" },
          { "name": "Ngày đăng:", "content": "Thứ 2, 01:25 13/05/2024" },
          { "name": "Ngày hết hạn:", "content": "Thứ 7, 01:25 18/05/2024" }
        ]
      },
      "contact": {
        "header": { "header": "Thông tin liên hệ" },
        "content": [
          { "name": "Liên hệ:", "content": "Nguyễn Minh Trực" },
          { "name": "Điện thoại:", "content": "0797787910" },
          { "name": "Zalo", "content": "0797787910" }
        ]
      }
    },
    {
      "images": [
        {
          "img": "https://pt123.cdn.static123.com/images/thumbs/900x600/fit/2024/04/16/z5103292367350-74d2218de948e13398a2f509425b76aa_1713210566.jpg",
          "alt": "căn hộ CAO CẤP THOÁNG MÁT HIỆN ĐAỊ AN NINH MỚI ngay TRUNG TÂM QUẬN 3"
        },
        {
          "img": "https://pt123.cdn.static123.com/images/thumbs/900x600/fit/2024/04/16/z5103292367145-c0eeaed2ebb83e4a6b91f1959fe82ecf_1713210566.jpg",
          "alt": "căn hộ CAO CẤP THOÁNG MÁT HIỆN ĐAỊ AN NINH MỚI ngay TRUNG TÂM QUẬN 3"
        },
        {
          "img": "https://pt123.cdn.static123.com/images/thumbs/900x600/fit/2024/04/16/z5103292320274-b150e440cf99430f379737f64b6a7ce9_1713210564.jpg",
          "alt": "căn hộ CAO CẤP THOÁNG MÁT HIỆN ĐAỊ AN NINH MỚI ngay TRUNG TÂM QUẬN 3"
        },
        {
          "img": "https://pt123.cdn.static123.com/images/thumbs/900x600/fit/2024/04/16/z5103292320144-32378ccfd37867ceb9eb138d2da3a348_1713210564.jpg",
          "alt": "căn hộ CAO CẤP THOÁNG MÁT HIỆN ĐAỊ AN NINH MỚI ngay TRUNG TÂM QUẬN 3"
        },
        {
          "img": "https://pt123.cdn.static123.com/images/thumbs/900x600/fit/2024/04/16/z5103292320765-99c10e18828d066611a9972fb7d7a412_1713210565.jpg",
          "alt": "căn hộ CAO CẤP THOÁNG MÁT HIỆN ĐAỊ AN NINH MỚI ngay TRUNG TÂM QUẬN 3"
        },
        {
          "img": "https://pt123.cdn.static123.com/images/thumbs/900x600/fit/2024/04/16/z5103292320888-0b3be15132c6a5ebe7f04303a439256f_1713210565.jpg",
          "alt": "căn hộ CAO CẤP THOÁNG MÁT HIỆN ĐAỊ AN NINH MỚI ngay TRUNG TÂM QUẬN 3"
        },
        {
          "img": "https://pt123.cdn.static123.com/images/thumbs/900x600/fit/2024/04/16/z5103292366712-703965122e16710ba6a2af5fbfc59686_1713210566.jpg",
          "alt": "căn hộ CAO CẤP THOÁNG MÁT HIỆN ĐAỊ AN NINH MỚI ngay TRUNG TÂM QUẬN 3"
        },
        {
          "img": "https://pt123.cdn.static123.com/images/thumbs/900x600/fit/2024/04/16/z5103292367203-7639ed25a70f9b9355a77e3722fb22df_1713210566.jpg",
          "alt": "căn hộ CAO CẤP THOÁNG MÁT HIỆN ĐAỊ AN NINH MỚI ngay TRUNG TÂM QUẬN 3"
        },
        {
          "img": "https://pt123.cdn.static123.com/images/thumbs/900x600/fit/2024/04/16/z5103292367350-74d2218de948e13398a2f509425b76aa_1713210566.jpg",
          "alt": "căn hộ CAO CẤP THOÁNG MÁT HIỆN ĐAỊ AN NINH MỚI ngay TRUNG TÂM QUẬN 3"
        },
        {
          "img": "https://pt123.cdn.static123.com/images/thumbs/900x600/fit/2024/04/16/z5103292367145-c0eeaed2ebb83e4a6b91f1959fe82ecf_1713210566.jpg",
          "alt": "căn hộ CAO CẤP THOÁNG MÁT HIỆN ĐAỊ AN NINH MỚI ngay TRUNG TÂM QUẬN 3"
        }
      ],
      "headerDetail": {
        "title": "căn hộ CAO CẤP THOÁNG MÁT HIỆN ĐAỊ AN NINH MỚI ngay TRUNG TÂM QUẬN 3",
        "class": {
          "content": "Chuyên mục: Cho thuê căn hộ dịch vụ Quận 3",
          "classType": "Cho thuê căn hộ dịch vụ Quận 3"
        },
        "address": "Địa chỉ: Cách Mạng Tháng Tám, Phường 10, Quận 3, Hồ Chí Minh",
        "attributes": {
          "price": "6.7 triệu/tháng",
          "acreage": "45m2",
          "published": "11 giờ trước",
          "hashtag": "621368"
        }
      },
      "mainContent": {
        "header": { "header": "Thông tin mô tả" },
        "content": [
          "Khai trương SIÊU PHẨM PHÒNG TRỌ CAO CẤP FULL NỘI THẤT MỚI 100% THOÁNG MÁT ngay CÁCH MẠNG THÁNG 8, VÒNG XOAY ĐIỆN BIÊN PHỦ, LÝ CHÍNH THẮNG, ĐIỆN BIÊN PHỦ Q3....",
          "GIÁ CHỈ 4TR3 4TR6 4TR8 5TR (còn thương lượng cho khách thiện chí)",
          "- Nội thất mới, diện tích rộng",
          "- An ninh, thoáng mát",
          "- Hệ thống PCCC đã được kiểm duyệt",
          "Liên hệ: Minh Trực (hỗ trợ tìm phòng dễ thương nhất hệ mặt trời)"
        ]
      },
      "overView": {
        "header": { "header": "Đặc điểm tin đăng" },
        "content": [
          { "name": "Mã tin:", "content": "#621368" },
          {
            "name": "Khu vực",
            "content": "Cho thuê căn hộ dịch vụ Hồ Chí Minh"
          },
          { "name": "Loại tin rao:", "content": "Cho thuê căn hộ dịch vụ" },
          { "name": "Đối tượng thuê:", "content": "Tất cả" },
          { "name": "Gói tin:", "content": "Tin thường" },
          { "name": "Ngày đăng:", "content": "Thứ 2, 01:24 13/05/2024" },
          { "name": "Ngày hết hạn:", "content": "Thứ 7, 01:24 18/05/2024" }
        ]
      },
      "contact": {
        "header": { "header": "Thông tin liên hệ" },
        "content": [
          { "name": "Liên hệ:", "content": "Nguyễn Minh Trực" },
          { "name": "Điện thoại:", "content": "0797787910" },
          { "name": "Zalo", "content": "0797787910" }
        ]
      }
    },
    {
      "images": [
        {
          "img": "https://pt123.cdn.static123.com/images/thumbs/900x600/fit/2024/05/13/z4235633330442-03331afbf8d007459e67db055f5aedab_1715538086.jpg",
          "alt": "khai trương căn hộ MỚI SANG TIỆN NGHI THOÁNG RẺ ngay Thành Thái"
        },
        {
          "img": "https://pt123.cdn.static123.com/images/thumbs/900x600/fit/2024/05/13/z4235633328510-e60a814ec4061f479b6cc834336e8a2a_1715538086.jpg",
          "alt": "khai trương căn hộ MỚI SANG TIỆN NGHI THOÁNG RẺ ngay Thành Thái"
        },
        {
          "img": "https://pt123.cdn.static123.com/images/thumbs/900x600/fit/2024/05/13/z4235633318879-d9013545d8cab21602d903a462128382_1715538085.jpg",
          "alt": "khai trương căn hộ MỚI SANG TIỆN NGHI THOÁNG RẺ ngay Thành Thái"
        },
        {
          "img": "https://pt123.cdn.static123.com/images/thumbs/900x600/fit/2024/05/13/z4235633315170-54f456ecccc17880480222ab4139cba7_1715538084.jpg",
          "alt": "khai trương căn hộ MỚI SANG TIỆN NGHI THOÁNG RẺ ngay Thành Thái"
        },
        {
          "img": "https://pt123.cdn.static123.com/images/thumbs/900x600/fit/2024/05/13/z4235633315662-bdee17e4d56ec1d91f46fcb289d40dff_1715538084.jpg",
          "alt": "khai trương căn hộ MỚI SANG TIỆN NGHI THOÁNG RẺ ngay Thành Thái"
        },
        {
          "img": "https://pt123.cdn.static123.com/images/thumbs/900x600/fit/2024/05/13/z4235633318424-1deac59855afac71197847fb61f33645_1715538085.jpg",
          "alt": "khai trương căn hộ MỚI SANG TIỆN NGHI THOÁNG RẺ ngay Thành Thái"
        },
        {
          "img": "https://pt123.cdn.static123.com/images/thumbs/900x600/fit/2024/05/13/z4235633321568-ceb49bf76f54b36c4134c2afe90b4b37_1715538086.jpg",
          "alt": "khai trương căn hộ MỚI SANG TIỆN NGHI THOÁNG RẺ ngay Thành Thái"
        },
        {
          "img": "https://pt123.cdn.static123.com/images/thumbs/900x600/fit/2024/05/13/z4235633325349-03622cdda3d2eb72fb1bfcc09bd3d019_1715538086.jpg",
          "alt": "khai trương căn hộ MỚI SANG TIỆN NGHI THOÁNG RẺ ngay Thành Thái"
        },
        {
          "img": "https://pt123.cdn.static123.com/images/thumbs/900x600/fit/2024/05/13/z4235633330442-03331afbf8d007459e67db055f5aedab_1715538086.jpg",
          "alt": "khai trương căn hộ MỚI SANG TIỆN NGHI THOÁNG RẺ ngay Thành Thái"
        },
        {
          "img": "https://pt123.cdn.static123.com/images/thumbs/900x600/fit/2024/05/13/z4235633328510-e60a814ec4061f479b6cc834336e8a2a_1715538086.jpg",
          "alt": "khai trương căn hộ MỚI SANG TIỆN NGHI THOÁNG RẺ ngay Thành Thái"
        }
      ],
      "headerDetail": {
        "title": "khai trương căn hộ MỚI SANG TIỆN NGHI THOÁNG RẺ ngay Thành Thái",
        "class": {
          "content": "Chuyên mục: Cho thuê căn hộ dịch vụ Quận 10",
          "classType": "Cho thuê căn hộ dịch vụ Quận 10"
        },
        "address": "Địa chỉ: Đường Tô Hiến Thành, Phường 13, Quận 10, Hồ Chí Minh",
        "attributes": {
          "price": "5.1 triệu/tháng",
          "acreage": "45m2",
          "published": "11 giờ trước",
          "hashtag": "641752"
        }
      },
      "mainContent": {
        "header": { "header": "Thông tin mô tả" },
        "content": [
          "Vị Trí căn hộ: Đường Thành Thái, P14. Quận 10",
          "Giá chỉ từ 4tr5 - 5tr3 - 5tr5",
          "- ĐA DẠNG CÁC LOẠI PHÒNG ỐC THEO Ý CỦA KHÁCH HÀNG",
          "- VỚI GIÁ CẢ HỢP LÝ, HỖ TRỢ KHÁCH NHIỆT TÌNH...",
          "- HỆ THỐNG PCCC ĐÃ ĐƯỢC KIỂM DUYỆT",
          "- AN NINH CHẤT LƯỢNG DỊCH VỤ TỐT",
          "- Vị trí gần trục đường lớn Cách Mạng Tháng Tám, Thành Thái, Lý Thường Kiệt, Tô Hiến Thành...",
          "- Tiện di chuyển qua các quận 1, quận 3, quận10, quận 5, quận 4",
          "Tổng quan :",
          "- Nội Thất Đầy Đủ: Tủ Lạnh, Máy Lạnh, Máy Giặt, Máy Nóng Lạnh, Lò Vi Sóng, Bếp Điện, Bộ Sofa, Bàn Ghế, Nệm, Kệ Tủ….",
          "- Căn hộ studio có ban công, cửa sổ thoáng đầy đủ tiện nghi",
          "- Ra vào bằng vân tay, giờ giấc tự do, Camera 24/7",
          "• Full nội thất, xách vali vào ở thôi",
          "• Hầm xe rộng, Ra vào vân tay",
          "• Camera an ninh cao, yên tĩnh",
          "• Giờ giấc tự do, Không chung chủ",
          "• Giặt sấy Riêng",
          "Chi phí bao gồm",
          "- Điện",
          "- Nước",
          "- Phí dịch vụ"
        ]
      },
      "overView": {
        "header": { "header": "Đặc điểm tin đăng" },
        "content": [
          { "name": "Mã tin:", "content": "#641752" },
          {
            "name": "Khu vực",
            "content": "Cho thuê căn hộ dịch vụ Hồ Chí Minh"
          },
          { "name": "Loại tin rao:", "content": "Cho thuê căn hộ dịch vụ" },
          { "name": "Đối tượng thuê:", "content": "Tất cả" },
          { "name": "Gói tin:", "content": "Tin thường" },
          { "name": "Ngày đăng:", "content": "Thứ 2, 01:21 13/05/2024" },
          { "name": "Ngày hết hạn:", "content": "Thứ 7, 01:21 18/05/2024" }
        ]
      },
      "contact": {
        "header": { "header": "Thông tin liên hệ" },
        "content": [
          { "name": "Liên hệ:", "content": "Nguyễn Minh Trực" },
          { "name": "Điện thoại:", "content": "0797787910" },
          { "name": "Zalo", "content": "0797787910" }
        ]
      }
    },
    {
      "images": [
        {
          "img": "https://pt123.cdn.static123.com/images/thumbs/900x600/fit/2024/05/13/z5049657115349-aed688d87478e8a06aeea3175f80bd56_1715538016.jpg",
          "alt": "siêu phẩm CĂN HỘ LUXURY THOÁNG ĐẸP SANG ngay PHAN ĐÌNH PHÙNG"
        },
        {
          "img": "https://pt123.cdn.static123.com/images/thumbs/900x600/fit/2024/05/13/z5049657110566-7c1d769aeba9fb8e5d7fb6daff8969f3_1715538012.jpg",
          "alt": "siêu phẩm CĂN HỘ LUXURY THOÁNG ĐẸP SANG ngay PHAN ĐÌNH PHÙNG"
        },
        {
          "img": "https://pt123.cdn.static123.com/images/thumbs/900x600/fit/2024/05/13/z5049657113070-3b5c2556973b69c86cc66921f5df4db6_1715538012.jpg",
          "alt": "siêu phẩm CĂN HỘ LUXURY THOÁNG ĐẸP SANG ngay PHAN ĐÌNH PHÙNG"
        },
        {
          "img": "https://pt123.cdn.static123.com/images/thumbs/900x600/fit/2024/05/13/z5049657113253-d4da177293d05538059be2ea39aef9c0_1715538013.jpg",
          "alt": "siêu phẩm CĂN HỘ LUXURY THOÁNG ĐẸP SANG ngay PHAN ĐÌNH PHÙNG"
        },
        {
          "img": "https://pt123.cdn.static123.com/images/thumbs/900x600/fit/2024/05/13/z5049657113472-038ab224f6dff08570591d3da28331c6_1715538013.jpg",
          "alt": "siêu phẩm CĂN HỘ LUXURY THOÁNG ĐẸP SANG ngay PHAN ĐÌNH PHÙNG"
        },
        {
          "img": "https://pt123.cdn.static123.com/images/thumbs/900x600/fit/2024/05/13/z5049657113805-affd2fbe8327fcdc2ce3cb38a66133b5_1715538014.jpg",
          "alt": "siêu phẩm CĂN HỘ LUXURY THOÁNG ĐẸP SANG ngay PHAN ĐÌNH PHÙNG"
        },
        {
          "img": "https://pt123.cdn.static123.com/images/thumbs/900x600/fit/2024/05/13/z5049657114144-d5c59729c59c3cc2d679f95e845e0734_1715538014.jpg",
          "alt": "siêu phẩm CĂN HỘ LUXURY THOÁNG ĐẸP SANG ngay PHAN ĐÌNH PHÙNG"
        },
        {
          "img": "https://pt123.cdn.static123.com/images/thumbs/900x600/fit/2024/05/13/z5049657114978-6793a95bbf6091f86222431ce30f839e_1715538015.jpg",
          "alt": "siêu phẩm CĂN HỘ LUXURY THOÁNG ĐẸP SANG ngay PHAN ĐÌNH PHÙNG"
        },
        {
          "img": "https://pt123.cdn.static123.com/images/thumbs/900x600/fit/2024/05/13/z5049657115349-aed688d87478e8a06aeea3175f80bd56_1715538016.jpg",
          "alt": "siêu phẩm CĂN HỘ LUXURY THOÁNG ĐẸP SANG ngay PHAN ĐÌNH PHÙNG"
        },
        {
          "img": "https://pt123.cdn.static123.com/images/thumbs/900x600/fit/2024/05/13/z5049657110566-7c1d769aeba9fb8e5d7fb6daff8969f3_1715538012.jpg",
          "alt": "siêu phẩm CĂN HỘ LUXURY THOÁNG ĐẸP SANG ngay PHAN ĐÌNH PHÙNG"
        }
      ],
      "headerDetail": {
        "title": "siêu phẩm CĂN HỘ LUXURY THOÁNG ĐẸP SANG ngay PHAN ĐÌNH PHÙNG",
        "class": {
          "content": "Chuyên mục: Cho thuê căn hộ dịch vụ Quận Phú Nhuận",
          "classType": "Cho thuê căn hộ dịch vụ Quận Phú Nhuận"
        },
        "address": "Địa chỉ: Đường Phan Đình Phùng, Phường 1, Quận Phú Nhuận, Hồ Chí Minh",
        "attributes": {
          "price": "8.7 triệu/tháng",
          "acreage": "65m2",
          "published": "11 giờ trước",
          "hashtag": "640740"
        }
      },
      "mainContent": {
        "header": { "header": "Thông tin mô tả" },
        "content": [
          "Vị Trí căn hộ: Đường PHAN ĐÌNH PHÙNG, Phường 15 Quận PHÚ NHUẬN",
          "Giá chỉ từ 8.000.000Đ - 9.000.000Đ - 10.000.000Đ",
          "- ĐA DẠNG CÁC LOẠI PHÒNG ỐC THEO Ý CỦA KHÁCH HÀNG",
          "- VỚI GIÁ CẢ HỢP LÝ, HỖ TRỢ KHÁCH NHIỆT TÌNH...",
          "- HỆ THỐNG PCCC ĐÃ ĐƯỢC KIỂM DUYỆT",
          "- AN NINH CHẤT LƯỢNG DỊCH VỤ TỐT",
          "- Vị trí gần trục đường lớn PHAN ĐÌNH PHÙNG, NGUYỄN VĂN TRỖI, HAI BÀ TRƯNG, SÂN BAY TÂN SƠN NHẤT, PHAN XÍCH LONG....",
          "- Tiện di chuyển qua các quận 1, quận 3, quận10, quận 5, quận 4",
          "Tổng quan :",
          "- Nội Thất Đầy Đủ: Tủ Lạnh, Máy Lạnh, Máy Giặt, Máy Nóng Lạnh, Lò Vi Sóng, Bếp Điện, Bộ Sofa, Bàn Ghế, Nệm, Kệ Tủ….",
          "- Căn hộ studio có ban công, cửa sổ thoáng đầy đủ tiện nghi",
          "- Ra vào bằng vân tay, giờ giấc tự do, Camera 24/7",
          "• Full nội thất, xách vali vào ở thôi",
          "• Hầm xe rộng, Ra vào vân tay",
          "• Camera an ninh cao, yên tĩnh",
          "• Giờ giấc tự do, Không chung chủ",
          "• Giặt sấy Riêng",
          "Chi phí bao gồm",
          "- Điện",
          "- Nước",
          "- Phí dịch vụ"
        ]
      },
      "overView": {
        "header": { "header": "Đặc điểm tin đăng" },
        "content": [
          { "name": "Mã tin:", "content": "#640740" },
          {
            "name": "Khu vực",
            "content": "Cho thuê căn hộ dịch vụ Hồ Chí Minh"
          },
          { "name": "Loại tin rao:", "content": "Cho thuê căn hộ dịch vụ" },
          { "name": "Đối tượng thuê:", "content": "Tất cả" },
          { "name": "Gói tin:", "content": "Tin thường" },
          { "name": "Ngày đăng:", "content": "Thứ 2, 01:20 13/05/2024" },
          { "name": "Ngày hết hạn:", "content": "Thứ 7, 01:20 18/05/2024" }
        ]
      },
      "contact": {
        "header": { "header": "Thông tin liên hệ" },
        "content": [
          { "name": "Liên hệ:", "content": "Nguyễn Minh Trực" },
          { "name": "Điện thoại:", "content": "0797787910" },
          { "name": "Zalo", "content": "0797787910" }
        ]
      }
    },
    {
      "images": [
        {
          "img": "https://pt123.cdn.static123.com/images/thumbs/900x600/fit/2024/05/13/5_1715535565.jpg",
          "alt": "PHÒNG STUDIO FULL NT - BAN CÔNG NGAY GIGAMALL - PHẠM VĂN ĐỒNG TD"
        },
        {
          "img": "https://pt123.cdn.static123.com/images/thumbs/900x600/fit/2024/05/13/1_1715535561.jpg",
          "alt": "PHÒNG STUDIO FULL NT - BAN CÔNG NGAY GIGAMALL - PHẠM VĂN ĐỒNG TD"
        },
        {
          "img": "https://pt123.cdn.static123.com/images/thumbs/900x600/fit/2024/05/13/2_1715535561.jpg",
          "alt": "PHÒNG STUDIO FULL NT - BAN CÔNG NGAY GIGAMALL - PHẠM VĂN ĐỒNG TD"
        },
        {
          "img": "https://pt123.cdn.static123.com/images/thumbs/900x600/fit/2024/05/13/3_1715535563.jpg",
          "alt": "PHÒNG STUDIO FULL NT - BAN CÔNG NGAY GIGAMALL - PHẠM VĂN ĐỒNG TD"
        },
        {
          "img": "https://pt123.cdn.static123.com/images/thumbs/900x600/fit/2024/05/13/4_1715535563.jpg",
          "alt": "PHÒNG STUDIO FULL NT - BAN CÔNG NGAY GIGAMALL - PHẠM VĂN ĐỒNG TD"
        },
        {
          "img": "https://pt123.cdn.static123.com/images/thumbs/900x600/fit/2024/05/13/5_1715535565.jpg",
          "alt": "PHÒNG STUDIO FULL NT - BAN CÔNG NGAY GIGAMALL - PHẠM VĂN ĐỒNG TD"
        },
        {
          "img": "https://pt123.cdn.static123.com/images/thumbs/900x600/fit/2024/05/13/1_1715535561.jpg",
          "alt": "PHÒNG STUDIO FULL NT - BAN CÔNG NGAY GIGAMALL - PHẠM VĂN ĐỒNG TD"
        }
      ],
      "headerDetail": {
        "title": "PHÒNG STUDIO FULL NT - BAN CÔNG NGAY GIGAMALL - PHẠM VĂN ĐỒNG TD",
        "class": {
          "content": "Chuyên mục: Cho thuê căn hộ dịch vụ Thủ Đức",
          "classType": "Cho thuê căn hộ dịch vụ Thủ Đức"
        },
        "address": "Địa chỉ: 20, Phường Hiệp Bình Chánh, Thủ Đức, Hồ Chí Minh",
        "attributes": {
          "price": "6.8 triệu/tháng",
          "acreage": "30m2",
          "published": "11 giờ trước",
          "hashtag": "654580"
        }
      },
      "mainContent": {
        "header": { "header": "Thông tin mô tả" },
        "content": [
          "PHÒNG STUDIO FULL NT - BAN CÔNG NGAY GIGAMALL - PHẠM VĂN ĐỒNG TD",
          "Vị trí: đường 26, Hiệp Bình Chánh, Thủ Đức",
          "mất 2 phút tới, QL13, Gigamall, Pham Văn Đồng, ...",
          "Phòng lớn 40m2 ở dc 3-4 người, đầu tháng 6 trống",
          "phòng ban công siêu thoáng, nội thất xịn xò",
          "giờ giấc tự do, ra vào vân tay",
          "có hầm xe riêng",
          "giá thuê 6tr*",
          "call/zalo/sms 0335.782.169"
        ]
      },
      "overView": {
        "header": { "header": "Đặc điểm tin đăng" },
        "content": [
          { "name": "Mã tin:", "content": "#654580" },
          {
            "name": "Khu vực",
            "content": "Cho thuê căn hộ dịch vụ Hồ Chí Minh"
          },
          { "name": "Loại tin rao:", "content": "Cho thuê căn hộ dịch vụ" },
          { "name": "Đối tượng thuê:", "content": "Tất cả" },
          { "name": "Gói tin:", "content": "Tin thường" },
          { "name": "Ngày đăng:", "content": "Thứ 2, 00:40 13/05/2024" },
          { "name": "Ngày hết hạn:", "content": "Thứ 7, 00:40 18/05/2024" }
        ]
      },
      "contact": {
        "header": { "header": "Thông tin liên hệ" },
        "content": [
          { "name": "Liên hệ:", "content": "Nguyễn Thị Thanh Tuyền" },
          { "name": "Điện thoại:", "content": "0335782169" },
          { "name": "Zalo", "content": "0335782169" }
        ]
      }
    },
    {
      "images": [
        {
          "img": "https://pt123.cdn.static123.com/images/thumbs/900x600/fit/2023/11/27/p1011_1701096656.jpg",
          "alt": "Phòng cho thuê full nội thất, Trần Khánh Dư, P.Tân Định ,Quận 1"
        },
        {
          "img": "https://pt123.cdn.static123.com/images/thumbs/900x600/fit/2023/11/27/p3011_1701096658.jpg",
          "alt": "Phòng cho thuê full nội thất, Trần Khánh Dư, P.Tân Định ,Quận 1"
        },
        {
          "img": "https://pt123.cdn.static123.com/images/thumbs/900x600/fit/2023/11/27/p2011_1701096656.jpg",
          "alt": "Phòng cho thuê full nội thất, Trần Khánh Dư, P.Tân Định ,Quận 1"
        },
        {
          "img": "https://pt123.cdn.static123.com/images/thumbs/900x600/fit/2023/11/27/p1011_1701096656.jpg",
          "alt": "Phòng cho thuê full nội thất, Trần Khánh Dư, P.Tân Định ,Quận 1"
        },
        {
          "img": "https://pt123.cdn.static123.com/images/thumbs/900x600/fit/2023/11/27/p3011_1701096658.jpg",
          "alt": "Phòng cho thuê full nội thất, Trần Khánh Dư, P.Tân Định ,Quận 1"
        }
      ],
      "headerDetail": {
        "title": "Phòng cho thuê full nội thất, Trần Khánh Dư, P.Tân Định ,Quận 1",
        "class": {
          "content": "Chuyên mục: Cho thuê căn hộ dịch vụ Quận 1",
          "classType": "Cho thuê căn hộ dịch vụ Quận 1"
        },
        "address": "Địa chỉ: Trần Khánh Dư, Phường Tân Định, Quận 1, Hồ Chí Minh",
        "attributes": {
          "price": "5 triệu/tháng",
          "acreage": "20m2",
          "published": "13 giờ trước",
          "hashtag": "641284"
        }
      },
      "mainContent": {
        "header": { "header": "Thông tin mô tả" },
        "content": [
          "Chính chủ cho thuê:",
          "- Đường Trần Khánh Dư, P. Tân Định, Q1.",
          "+ Nội thất cao cấp, máy giặt chung... Có cửa sổ lớn.",
          "+ Giờ giấc tự do, không chung chủ, để xe free, vân tay, camera an ninh...",
          "+ Gần CĐ Nghề TP. HCM, Hoàng Sa, chợ Tân Định...",
          "+ Hẻm ôtô, an ninh, yên tĩnh.",
          "- Giá 5tr",
          "- LH: 0948100993 (zalo) Khánh chủ nhà."
        ]
      },
      "overView": {
        "header": { "header": "Đặc điểm tin đăng" },
        "content": [
          { "name": "Mã tin:", "content": "#641284" },
          {
            "name": "Khu vực",
            "content": "Cho thuê căn hộ dịch vụ Hồ Chí Minh"
          },
          { "name": "Loại tin rao:", "content": "Cho thuê căn hộ dịch vụ" },
          { "name": "Đối tượng thuê:", "content": "Tất cả" },
          { "name": "Gói tin:", "content": "Tin thường" },
          { "name": "Ngày đăng:", "content": "Chủ Nhật, 22:54 12/05/2024" },
          { "name": "Ngày hết hạn:", "content": "Thứ 6, 22:54 17/05/2024" }
        ]
      },
      "contact": {
        "header": { "header": "Thông tin liên hệ" },
        "content": [
          { "name": "Liên hệ:", "content": "A.Khánh chủ nhà" },
          { "name": "Điện thoại:", "content": "0948100993" },
          { "name": "Zalo", "content": "0948100993" }
        ]
      }
    },
    {
      "images": [
        {
          "img": "https://pt123.cdn.static123.com/images/thumbs/900x600/fit/2024/05/12/z2912348524492-c35a918e1ee7b4a959fe6aed6e9c2eec_1715528788.jpg",
          "alt": "Căn hộ dịch vụ ban công full nội thất tại Phú Nhuận"
        },
        {
          "img": "https://pt123.cdn.static123.com/images/thumbs/900x600/fit/2024/05/12/z2912348513252-9f511e0332a9fcef3c0eec9661244c99_1715528786.jpg",
          "alt": "Căn hộ dịch vụ ban công full nội thất tại Phú Nhuận"
        },
        {
          "img": "https://pt123.cdn.static123.com/images/thumbs/900x600/fit/2024/05/12/z2912348523567-b68907d919df502bda9cfd6ffe417371_1715528786.jpg",
          "alt": "Căn hộ dịch vụ ban công full nội thất tại Phú Nhuận"
        },
        {
          "img": "https://pt123.cdn.static123.com/images/thumbs/900x600/fit/2024/05/12/z2912348523672-f290b8022a703fd507589524f9bd148d_1715528787.jpg",
          "alt": "Căn hộ dịch vụ ban công full nội thất tại Phú Nhuận"
        },
        {
          "img": "https://pt123.cdn.static123.com/images/thumbs/900x600/fit/2024/05/12/z2912348524492-c35a918e1ee7b4a959fe6aed6e9c2eec_1715528788.jpg",
          "alt": "Căn hộ dịch vụ ban công full nội thất tại Phú Nhuận"
        },
        {
          "img": "https://pt123.cdn.static123.com/images/thumbs/900x600/fit/2024/05/12/z2912348513252-9f511e0332a9fcef3c0eec9661244c99_1715528786.jpg",
          "alt": "Căn hộ dịch vụ ban công full nội thất tại Phú Nhuận"
        }
      ],
      "headerDetail": {
        "title": "Căn hộ dịch vụ ban công full nội thất tại Phú Nhuận",
        "class": {
          "content": "Chuyên mục: Cho thuê căn hộ dịch vụ Quận Phú Nhuận",
          "classType": "Cho thuê căn hộ dịch vụ Quận Phú Nhuận"
        },
        "address": "Địa chỉ: 129/1/2 Đường Hoàng Văn Thụ, Phường 8, Quận Phú Nhuận, Hồ Chí Minh",
        "attributes": {
          "price": "4.5 triệu/tháng",
          "acreage": "20m2",
          "published": "13 giờ trước",
          "hashtag": "649374"
        }
      },
      "mainContent": {
        "header": { "header": "Thông tin mô tả" },
        "content": [
          "- Hẻm lớn, vị trí trung tâm, giao thông thuận tiện đi các quận",
          "- Có thang máy, an ninh",
          "- Tủ quần áo. - Máy lạnh - Bếp riêng. - Toilet bên trong phòng - máy nước nóng - Khóa vân tay - Hầm gửi xe.",
          "- Các chi phí : điện 4k/kw. nước 100k/người, dịch vụ 150k ( CÒN LẠI FREE)",
          "- ĐỊA CHỈ : Hoàng Văn Thụ, P8, Phú Nhuận",
          "( CHÍNH CHỦ)"
        ]
      },
      "overView": {
        "header": { "header": "Đặc điểm tin đăng" },
        "content": [
          { "name": "Mã tin:", "content": "#649374" },
          {
            "name": "Khu vực",
            "content": "Cho thuê căn hộ dịch vụ Hồ Chí Minh"
          },
          { "name": "Loại tin rao:", "content": "Cho thuê căn hộ dịch vụ" },
          { "name": "Đối tượng thuê:", "content": "Tất cả" },
          { "name": "Gói tin:", "content": "Tin thường" },
          { "name": "Ngày đăng:", "content": "Chủ Nhật, 22:48 12/05/2024" },
          { "name": "Ngày hết hạn:", "content": "Thứ 6, 22:48 17/05/2024" }
        ]
      },
      "contact": {
        "header": { "header": "Thông tin liên hệ" },
        "content": [
          { "name": "Liên hệ:", "content": "Tran Dung" },
          { "name": "Điện thoại:", "content": "0977844491" },
          { "name": "Zalo", "content": "0977844491" }
        ]
      }
    },
    {
      "images": [
        {
          "img": "https://pt123.cdn.static123.com/images/thumbs/900x600/fit/2024/05/12/img-20240512-084413_1715527892.jpg",
          "alt": "SIÊU PHẨM - APARTMENT - STUDIO - VIEW BIỂN TRIỆU ĐÔ - P.VĨNH THỌ, NHA TRANG"
        },
        {
          "img": "https://pt123.cdn.static123.com/images/thumbs/900x600/fit/2024/05/12/img-20240512-084402_1715527888.jpg",
          "alt": "SIÊU PHẨM - APARTMENT - STUDIO - VIEW BIỂN TRIỆU ĐÔ - P.VĨNH THỌ, NHA TRANG"
        },
        {
          "img": "https://pt123.cdn.static123.com/images/thumbs/900x600/fit/2024/05/12/img-20240512-084354_1715527888.jpg",
          "alt": "SIÊU PHẨM - APARTMENT - STUDIO - VIEW BIỂN TRIỆU ĐÔ - P.VĨNH THỌ, NHA TRANG"
        },
        {
          "img": "https://pt123.cdn.static123.com/images/thumbs/900x600/fit/2024/05/12/img-20240512-084352_1715527890.jpg",
          "alt": "SIÊU PHẨM - APARTMENT - STUDIO - VIEW BIỂN TRIỆU ĐÔ - P.VĨNH THỌ, NHA TRANG"
        },
        {
          "img": "https://pt123.cdn.static123.com/images/thumbs/900x600/fit/2024/05/12/img-20240512-084413_1715527892.jpg",
          "alt": "SIÊU PHẨM - APARTMENT - STUDIO - VIEW BIỂN TRIỆU ĐÔ - P.VĨNH THỌ, NHA TRANG"
        },
        {
          "img": "https://pt123.cdn.static123.com/images/thumbs/900x600/fit/2024/05/12/img-20240512-084402_1715527888.jpg",
          "alt": "SIÊU PHẨM - APARTMENT - STUDIO - VIEW BIỂN TRIỆU ĐÔ - P.VĨNH THỌ, NHA TRANG"
        }
      ],
      "headerDetail": {
        "title": "SIÊU PHẨM - APARTMENT - STUDIO - VIEW BIỂN TRIỆU ĐÔ - P.VĨNH THỌ, NHA TRANG",
        "class": {
          "content": "Chuyên mục: Cho thuê căn hộ Thành Phố Nha Trang",
          "classType": "Cho thuê căn hộ Thành Phố Nha Trang"
        },
        "address": "Địa chỉ: Bắc Sơn, Phường Vĩnh Thọ, Thành Phố Nha Trang, Khánh Hòa",
        "attributes": {
          "price": "3.5 triệu/tháng",
          "acreage": "30m2",
          "published": "14 giờ trước",
          "hashtag": "654573"
        }
      },
      "mainContent": {
        "header": { "header": "Thông tin mô tả" },
        "content": [
          "Siêu phẩm - APARTMENT - STUDIO - VIEW BIỂN TRIỆU ĐÔ - P.VĨNH THỌ, NHA TRANG",
          ": đường Bắc Sơn, Phường Vĩnh Thọ, Tp Nha Trang",
          "Giờ giấc tự do, thoải mái, camera 24/7, thang máy, nhiều ưu đãi tiện ích, dịch vụ, sân thượng, có hồ bơi view cực đỉnh, có khu vực nướng BBQ.",
          "Đa dạng loại phòng, giá cả hạt dẻ",
          "Được nuôi thú cưng, cửa sổ, ban công view biển",
          "Vị trí mặt đường, gần trường Đh Nha Trang, Đh Tôn Đức Thắng, quán ăn, cà phê, gần biển Hòn Chồng.",
          "Nội thất đầy đủ, tiện nghi: TV, máy giặt, tủ lạnh, máy lạnh, máy nước nóng, bếp điện, lò vi sóng,...",
          "Phí dịch vụ (rác, wifi, vệ sinh): 150.000/ phòng , Nước: 100.000/người. Điện: 5.000đ/kwh. Xe máy: free",
          "Hợp đồng: 1- 3 - 6 - 12 (Cọc 1 TT 1)",
          "️ : (Mess/Zalo) - Quỳnh Như - Để được tư vấn chi tiết và xem phòng.",
          "Megas - Help you find SWEET HOME - tư vấn cho thuê căn hộ - phòng trọ cao cấp Nha Trang."
        ]
      },
      "overView": {
        "header": { "header": "Đặc điểm tin đăng" },
        "content": [
          { "name": "Mã tin:", "content": "#654573" },
          { "name": "Khu vực", "content": "Cho thuê căn hộ Khánh Hòa" },
          { "name": "Loại tin rao:", "content": "Cho thuê căn hộ" },
          { "name": "Đối tượng thuê:", "content": "Tất cả" },
          { "name": "Gói tin:", "content": "Tin miễn phí" },
          { "name": "Ngày đăng:", "content": "Chủ Nhật, 22:31 12/05/2024" },
          { "name": "Ngày hết hạn:", "content": "Thứ 6, 22:31 17/05/2024" }
        ]
      },
      "contact": {
        "header": { "header": "Thông tin liên hệ" },
        "content": [
          { "name": "Liên hệ:", "content": "Quỳnh Như" },
          { "name": "Điện thoại:", "content": "0905175700" },
          { "name": "Zalo", "content": "0905175700" }
        ]
      }
    },
    {
      "images": [
        {
          "img": "https://pt123.cdn.static123.com/images/thumbs/900x600/fit/2023/11/11/z4866859826811-c4e749faa6bb6f51e3dc2cf79c055e4b_1699677488.jpg",
          "alt": "CĂN HỘ NGUYÊN TẦNG 3 ( Phòng ngủ, Phòng Khách, Bêp) 60M2"
        },
        {},
        {
          "img": "https://pt123.cdn.static123.com/images/thumbs/900x600/fit/2023/11/11/z4866859815654-275351a3b8a0b67a1b8a1e26a88787b6_1699677476.jpg",
          "alt": "CĂN HỘ NGUYÊN TẦNG 3 ( Phòng ngủ, Phòng Khách, Bêp) 60M2"
        },
        {
          "img": "https://pt123.cdn.static123.com/images/thumbs/900x600/fit/2023/11/11/z4866859813336-69837cf9f2c1d91a213bc1388fcc4202_1699677482.jpg",
          "alt": "CĂN HỘ NGUYÊN TẦNG 3 ( Phòng ngủ, Phòng Khách, Bêp) 60M2"
        },
        {
          "img": "https://pt123.cdn.static123.com/images/thumbs/900x600/fit/2023/11/11/z4866859814835-b5cc0fc2c3bd224db9c3f97965065bca_1699677482.jpg",
          "alt": "CĂN HỘ NGUYÊN TẦNG 3 ( Phòng ngủ, Phòng Khách, Bêp) 60M2"
        },
        {
          "img": "https://pt123.cdn.static123.com/images/thumbs/900x600/fit/2023/11/11/z4866859817844-9d239d4b668855bfc357073dfd667385_1699677485.jpg",
          "alt": "CĂN HỘ NGUYÊN TẦNG 3 ( Phòng ngủ, Phòng Khách, Bêp) 60M2"
        },
        {
          "img": "https://pt123.cdn.static123.com/images/thumbs/900x600/fit/2023/11/11/z4866859819379-3b4ed61ee6237b9946b77c676c2c60cf_1699677485.jpg",
          "alt": "CĂN HỘ NGUYÊN TẦNG 3 ( Phòng ngủ, Phòng Khách, Bêp) 60M2"
        },
        {
          "img": "https://pt123.cdn.static123.com/images/thumbs/900x600/fit/2023/11/11/z4866859824392-e7c75163dae793cd85d3958862074606_1699677488.jpg",
          "alt": "CĂN HỘ NGUYÊN TẦNG 3 ( Phòng ngủ, Phòng Khách, Bêp) 60M2"
        },
        {
          "img": "https://pt123.cdn.static123.com/images/thumbs/900x600/fit/2023/11/11/z4866859826811-c4e749faa6bb6f51e3dc2cf79c055e4b_1699677488.jpg",
          "alt": "CĂN HỘ NGUYÊN TẦNG 3 ( Phòng ngủ, Phòng Khách, Bêp) 60M2"
        },
        {}
      ],
      "headerDetail": {
        "title": "CĂN HỘ NGUYÊN TẦNG 3 ( Phòng ngủ, Phòng Khách, Bêp) 60M2",
        "class": {
          "content": "Chuyên mục: Cho thuê căn hộ dịch vụ Quận Bình Thạnh",
          "classType": "Cho thuê căn hộ dịch vụ Quận Bình Thạnh"
        },
        "address": "Địa chỉ: Đường Bùi Đình Túy, Phường 12, Quận Bình Thạnh, Hồ Chí Minh",
        "attributes": {
          "price": "8.5 triệu/tháng",
          "acreage": "60m2",
          "published": "14 giờ trước",
          "hashtag": "640086"
        }
      },
      "mainContent": {
        "header": { "header": "Thông tin mô tả" },
        "content": [
          "- CĂN HỘ NGUYÊN TẦNG 3: PHÒNG NGỦ, PHÒNG KHÁCH, BẾP, BAN CÔNG",
          "- TIỆN ÍCH : SÀN GỖ, WC RIÊNG, MÁY LẠNH, TỦ LẠNH, KỆ BẾP... ( Dọn vào là ở)",
          "- ĐỊA CHỈ : 160/25 Bùi Đình Tuý, P.12, Bình Thạnh",
          "- Các chi phí : điện 4k/kw. Nước 100k/người, Dịch vụ 200k",
          "CHÍNH CHỦ CHO THUÊ"
        ]
      },
      "overView": {
        "header": { "header": "Đặc điểm tin đăng" },
        "content": [
          { "name": "Mã tin:", "content": "#640086" },
          {
            "name": "Khu vực",
            "content": "Cho thuê căn hộ dịch vụ Hồ Chí Minh"
          },
          { "name": "Loại tin rao:", "content": "Cho thuê căn hộ dịch vụ" },
          { "name": "Đối tượng thuê:", "content": "Tất cả" },
          { "name": "Gói tin:", "content": "Tin thường" },
          { "name": "Ngày đăng:", "content": "Chủ Nhật, 22:18 12/05/2024" },
          { "name": "Ngày hết hạn:", "content": "Thứ 6, 22:18 17/05/2024" }
        ]
      },
      "contact": {
        "header": { "header": "Thông tin liên hệ" },
        "content": [
          { "name": "Liên hệ:", "content": "Tran Dung" },
          { "name": "Điện thoại:", "content": "0977844491" },
          { "name": "Zalo", "content": "0977844491" }
        ]
      }
    }
  ]
}
